[{"volume":"207.060825171002733214","floorPrice":"0.083","numOfSales":"2673.000000000000000000","numOwners":"2072","volumeChange":"-0.15741185338578959","totalSupply":"8878","name":"ANOMALY A.I. by Star Im","id":"Q29sbGVjdGlvblR5cGU6MzA5MzQwNzY=","url":"https://i.seadn.io/s/raw/files/4d8916440f28d1c85afbfcc6d687eacd.jpg?w=500&auto=format"},{"numOfSales":"356.000000000000000000","volume":"13.094650000000006784","floorPrice":"0.03","numOwners":"810","volumeChange":"3.3410199076372065","totalSupply":"4","name":"Parallel Battle Pass Cards","id":"Q29sbGVjdGlvblR5cGU6MzA3MzAzMDc=","url":"https://i.seadn.io/s/raw/files/93d9d6c15b41903ed124d673e2b5b651.png?w=500&auto=format"},{"volume":"8.583699799999976676","numOfSales":"253.000000000000000000","floorPrice":"0.0294","numOwners":"1713","volumeChange":"0.5500086315242001","totalSupply":"9999","name":"Skyborne - Genesis Immortals","id":"Q29sbGVjdGlvblR5cGU6Mjc4NTQzMTM=","url":"https://i.seadn.io/gcs/files/65b163eaee2f95a2c25bfbd9f2c898ca.gif?w=500&auto=format"},{"floorPrice":"0.031898","numOfSales":"346.000000000000000000","volume":"15.670075903310562992","numOwners":"3867","volumeChange":"-0.2049418473137928","totalSupply":"19999","name":"Nakamigos-CLOAKS","id":"Q29sbGVjdGlvblR5cGU6Mjk3MTUwNTM=","url":"https://i.seadn.io/gcs/files/777e28922e6c3cabf9e0786fd76c1118.png?w=500&auto=format"},{"volume":"2668.492244253954595479","floorPrice":"0.231","numOfSales":"11729.000000000000000000","numOwners":"3510","volumeChange":"2668.4922442539546","totalSupply":"10000","name":"Trademark by Jack Butcher","id":"Q29sbGVjdGlvblR5cGU6MzEwMTQ4ODM=","url":"https://i.seadn.io/s/raw/files/76978409238f7da640912e64ad4574a5.png?w=500&auto=format"},{"numOfSales":"243.000000000000000000","floorPrice":"0.2098","volume":"56.671840801000115562","numOwners":"2950","volumeChange":"0.4531237914922655","totalSupply":"8912","name":"RENGA","id":"Q29sbGVjdGlvblR5cGU6MTk3NTg4Mzc=","url":"https://i.seadn.io/gcs/files/f3b11e36be14a5d31c75b19d03996fed.gif?w=500&auto=format"},{"floorPrice":"0.1778","numOfSales":"380.000000000000000000","volume":"54.039819001999767067","numOwners":"2571","volumeChange":"0.7518549194764514","totalSupply":"9999","name":"Pirate Nation - Founder's Pirates","id":"Q29sbGVjdGlvblR5cGU6MjQ1OTcyNzg=","url":"https://i.seadn.io/gcs/files/9dd5c3df43bcd0861cead11bc988ce3d.gif?w=500&auto=format"},{"volume":"43.12299854999984916","numOfSales":"937.000000000000000000","floorPrice":"0.04489","numOwners":"2405","volumeChange":"9.68357189957883","totalSupply":"7775","name":"Degenheim","id":"Q29sbGVjdGlvblR5cGU6MjE3NjEwMzU=","url":"https://i.seadn.io/gcs/files/54b6f02960ef1f586ba644f21e320278.png?w=500&auto=format"},{"floorPrice":"1","volume":"161.352286699999922348","numOfSales":"183.000000000000000000","numOwners":"1320","volumeChange":"2.910084508099775","totalSupply":"2000","name":"Oh Ottie!","id":"Q29sbGVjdGlvblR5cGU6MjI1MDE3NDY=","url":"https://i.seadn.io/gcs/files/b00ac40b1be4c491b46a65a98fa21480.gif?w=500&auto=format"},{"floorPrice":"0.188798","numOfSales":"670.000000000000000000","volume":"122.422963603999789939","numOwners":"5543","volumeChange":"0.391894063122034","totalSupply":"19929","name":"Nakamigos","id":"Q29sbGVjdGlvblR5cGU6MjQxOTc3MTc=","url":"https://i.seadn.io/gcs/files/1619b033c453fe36c5d9e2ac451379a7.png?w=500&auto=format"},{"volume":"107.640748036798967746","numOfSales":"1654.000000000000000000","floorPrice":"0.089","numOwners":"1351","volumeChange":"0.21132713914939502","totalSupply":"2988","name":"Nounish Punk","id":"Q29sbGVjdGlvblR5cGU6MzA5MzQwMTQ=","url":"https://i.seadn.io/s/raw/files/799514999832edc6c36d4af6fcc334b6.jpg?w=500&auto=format"},{"volume":"7.580238041758788903","floorPrice":"0.01698","numOfSales":"501.000000000000000000","numOwners":"47240","volumeChange":"0.12959896044376604","totalSupply":"94743","name":"Gemesis","id":"Q29sbGVjdGlvblR5cGU6MjQ1NDU1NzI=","url":"https://i.seadn.io/gcs/files/7ed181433ee09174f09a0e31b563d313.png?w=500&auto=format"},{"numOfSales":"2168.000000000000000000","floorPrice":"0.039","volume":"83.914275973200986414","numOwners":"778","volumeChange":"42.318086346898944","totalSupply":"1483","name":"Echo of Intensity by Per Kristian Stoveland","id":"Q29sbGVjdGlvblR5cGU6MzA2NTE2ODA=","url":"https://i.seadn.io/gcs/files/dfcff7fdba6d1aa99640cb97dcfde708.png?w=500&auto=format"},{"numOfSales":"175.000000000000000000","volume":"39.064883329999986472","floorPrice":"0.011","numOwners":"4915","volumeChange":"0.5332008073220211","totalSupply":"1597","name":"Rare Pepe (2016 - 2018)","id":"Q29sbGVjdGlvblR5cGU6MjMzMjA2Mjc=","url":"https://i.seadn.io/gcs/files/b36c8411036867ffedd8d85c54079785.png?w=500&auto=format"},{"numOfSales":"298.000000000000000000","volume":"216.00287191999393599","floorPrice":"0.808750001","numOwners":"1891","volumeChange":"-0.2184572630005715","totalSupply":"5563","name":"Azuki Elemental Beans","id":"Q29sbGVjdGlvblR5cGU6MjcyNjMzNDE=","url":"https://i.seadn.io/gcs/files/f3a499dc27479c0c0fd6aaa3f6581561.gif?w=500&auto=format"},{"floorPrice":"0.199","numOfSales":"385.000000000000000000","volume":"70.221021999999919672","numOwners":"952","volumeChange":"167.93251217898577","totalSupply":"3448","name":"InfiniGods - InfiniPass","id":"Q29sbGVjdGlvblR5cGU6MTYzNTQzNzQ=","url":"https://i.seadn.io/gcs/files/78ef6d6911a5ea84baab623658846de6.gif?w=500&auto=format"},{"numOfSales":"167.000000000000000000","floorPrice":"0.0492","volume":"8.064470900999999969","numOwners":"8404","volumeChange":"-0.36967644254697735","totalSupply":"16019","name":"RTFKT x Nike Dunk Genesis CRYPTOKICKS","id":"Q29sbGVjdGlvblR5cGU6MTM3NDQ2NTA=","url":"https://i.seadn.io/gae/-j4h0B8cXDX2PqNlKf5DQQU9BJpJKv-FuW2q9zx2RNlG1cbgpBSsGck1UlZ2Z86Cm-ciw69OwstV_dH79HZ-idPunP9mkoSdxvABHU4?w=500&auto=format"},{"numOfSales":"323.000000000000000000","floorPrice":"0.133","volume":"36.166260000000001185","numOwners":"839","volumeChange":"4.7530937410620595","totalSupply":"2222","name":"pARticle pack","id":"Q29sbGVjdGlvblR5cGU6MzA4MzAxODM=","url":"https://i.seadn.io/s/raw/files/154d22c30b701affb312b7ce531809cb.png?w=500&auto=format"},{"numOfSales":"352.000000000000000000","floorPrice":"0.167598","volume":"55.906772999999787999","numOwners":"2802","volumeChange":"4.778063958829593","totalSupply":"7390","name":"Moonbirds: Mythics","id":"Q29sbGVjdGlvblR5cGU6Mjc4NDg2MDQ=","url":"https://i.seadn.io/gcs/files/fd53fbba20749f9c0ec9280c015235c5.png?w=500&auto=format"},{"floorPrice":"0.13","numOfSales":"169.000000000000000000","volume":"29.270336091357286534","numOwners":"140","volumeChange":"29.270336091357287","totalSupply":"300","name":"Naïve by Olga Fradina","id":"Q29sbGVjdGlvblR5cGU6MzA5NDAyNjg=","url":"https://i.seadn.io/s/raw/files/e595585959e07180bee4d4c15916ddc2.png?w=500&auto=format"},{"floorPrice":"2.261999","numOfSales":"512.000000000000000000","volume":"1105.052843720003238559","numOwners":"5558","volumeChange":"1.086695234698785","totalSupply":"9998","name":"Doodles Original Collection","id":"Q29sbGVjdGlvblR5cGU6MjIyNDM5MA==","url":"https://i.seadn.io/s/raw/files/c91c80bd4e7e8d9c01ae4cbd87c54cd7.png?w=500&auto=format"},{"numOfSales":"311.000000000000000000","floorPrice":"0.163999","volume":"44.338912000000028968","numOwners":"828","volumeChange":"102.83844458652135","totalSupply":"2902","name":"Defimons Apartments","id":"Q29sbGVjdGlvblR5cGU6MTkxMDE0MzU=","url":"https://i.seadn.io/gcs/files/19bb38b79b5db49b10da6bae9d59ba4a.png?w=500&auto=format"},{"volume":"70.473982829900037927","numOfSales":"408.000000000000000000","floorPrice":"0.215","numOwners":"1506","volumeChange":"1.464629419752845","totalSupply":"7500","name":"ChronoForge","id":"Q29sbGVjdGlvblR5cGU6NDY2ODk4NA==","url":"https://i.seadn.io/gcs/files/f9fd69f0ef630b0524a97212dfd71fb5.png?w=500&auto=format"},{"numOfSales":"297.000000000000000000","floorPrice":"1.39896","volume":"404.182413799999210369","numOwners":"6596","volumeChange":"0.28529664933222326","totalSupply":"19999","name":"Meebits","id":"Q29sbGVjdGlvblR5cGU6NTM2NTM1","url":"https://i.seadn.io/gcs/files/2d036c8c2bed042a1588622c3173677f.png?w=500&auto=format"},{"floorPrice":"0.825","volume":"196.139009000000015703","numOfSales":"261.000000000000000000","numOwners":"2019","volumeChange":"-0.21043171498121022","totalSupply":"5000","name":"Pixels - Farm Land","id":"Q29sbGVjdGlvblR5cGU6NjU0MTA0Mw==","url":"https://i.seadn.io/gcs/files/39bc09683242af3e70535579f36ddfd9.png?w=500&auto=format"},{"numOfSales":"740.000000000000000000","floorPrice":"0.7497","volume":"503.492523755000263463","numOwners":"4233","volumeChange":"1.3698486019066143","totalSupply":"11016","name":"y00ts","id":"Q29sbGVjdGlvblR5cGU6MzA4NDA3NTA=","url":"https://i.seadn.io/s/raw/files/2c36035682c874a7940051e79e8fe906.png?w=500&auto=format"},{"numOfSales":"404.000000000000000000","floorPrice":"0.041","volume":"13.062679389999978241","numOwners":"1208","volumeChange":"-0.9139022983462982","totalSupply":"6000","name":"FRACTIONAL UPRISING STUDIOS MEMBERSHIP","id":"Q29sbGVjdGlvblR5cGU6MjE5Nzc0MTY=","url":"https://i.seadn.io/gcs/files/531c10308f986587087bdb7dd1c3012b.png?w=500&auto=format"},{"numOfSales":"466.000000000000000000","volume":"13645.619754999976066756","floorPrice":"30.89","numOwners":"5547","volumeChange":"1.0601159296645388","totalSupply":"9998","name":"Bored Ape Yacht Club","id":"Q29sbGVjdGlvblR5cGU6NDg4NjIx","url":"https://i.seadn.io/gae/Ju9CkWtV-1Okvf45wo8UctR-M9He2PjILP0oOvxE89AyiPPGtrR3gysu1Zgy0hjd2xKIgjJJtWIc0ybj4Vd7wv8t3pxDGHoJBzDB?w=500&auto=format"},{"floorPrice":"0.0798","numOfSales":"160.000000000000000000","volume":"15.605570000000003716","numOwners":"12067","volumeChange":"0.7012856472878768","totalSupply":"38550","name":"Friendship Bracelets by Alexis André","id":"Q29sbGVjdGlvblR5cGU6MjE5NTY4NDI=","url":"https://i.seadn.io/gcs/files/01de134db029be955aa892ea066c085f.png?w=500&auto=format"},{"numOfSales":"1076.000000000000000000","volume":"72.977526871756040805","floorPrice":"0.0003","numOwners":"60466","volumeChange":"-0.15336346298219702","totalSupply":"1273","name":"Parallel Alpha","id":"Q29sbGVjdGlvblR5cGU6MjY0MDU2","url":"https://i.seadn.io/gae/Nnp8Pdo6EidK7eBduGnAn_JBvFsYGhNGMJ_fHJ_mzGMN_2Khu5snL5zmiUMcSsIqtANh19KqxXDs0iNq_aYbKC5smO3hiCSw9PlL?w=500&auto=format"},{"volume":"282.388889302700818007","numOfSales":"852.000000000000000000","floorPrice":"0.355","numOwners":"545","volumeChange":"0.3018422752004214","totalSupply":"1000","name":"Velocity Series: Velocity Pass","id":"Q29sbGVjdGlvblR5cGU6Mjc4NjE3NjQ=","url":"https://i.seadn.io/gcs/files/8a43aee9079fdbd79925c7c5ef3056b0.png?w=500&auto=format"},{"floorPrice":"0.529","volume":"183.994857499999767469","numOfSales":"421.000000000000000000","numOwners":"1026","volumeChange":"0.8924180321381661","totalSupply":"2222","name":"Mittaria Genesis","id":"Q29sbGVjdGlvblR5cGU6Mjk3MzA2ODI=","url":"https://i.seadn.io/gcs/files/a1eaa1c8aade72050b9f1198cbe5e215.png?w=500&auto=format"},{"floorPrice":"0.214950001","numOfSales":"643.000000000000000000","volume":"125.099521989999530547","numOwners":"1061","volumeChange":"0.5079708356988449","totalSupply":"6074","name":"Sugartown Oras","id":"Q29sbGVjdGlvblR5cGU6MjcwOTMyMDk=","url":"https://i.seadn.io/s/raw/files/045932f79c3036c05c3899651dd39a1c.png?w=500&auto=format"},{"floorPrice":"0.184949","numOfSales":"351.000000000000000000","volume":"59.401989000890040415","numOwners":"1386","volumeChange":"0.7060519263090768","totalSupply":"1","name":"My Keyboard","id":"Q29sbGVjdGlvblR5cGU6MjMwMDAwNzU=","url":"https://i.seadn.io/gcs/files/cb21a8bb565bed1e6ab6b6e878a05673.png?w=500&auto=format"},{"volume":"15.826342600000005589","numOfSales":"213.000000000000000000","floorPrice":"0.043","numOwners":"2150","volumeChange":"-0.4588363841706385","totalSupply":"9794","name":"8liens NFT","id":"Q29sbGVjdGlvblR5cGU6MTkwNTk2NzI=","url":"https://i.seadn.io/gcs/files/7c8d2909d2d0b9860e64921c36a1321a.gif?w=500&auto=format"},{"volume":"188.341051688798074792","numOfSales":"409.000000000000000000","floorPrice":"0.57","numOwners":"1025","volumeChange":"5.082370273244879","totalSupply":"2000","name":"San FranTokyo Genesis Pass","id":"Q29sbGVjdGlvblR5cGU6MjkwMzU1MTE=","url":"https://i.seadn.io/gcs/files/076759abbc078315cd77b947fba66b87.png?w=500&auto=format"},{"numOfSales":"376.000000000000000000","floorPrice":"0.119","volume":"34.037642199999950776","numOwners":"1236","volumeChange":"1.3748025346424009","totalSupply":"3333","name":"Skyborne - Nexian Gems","id":"Q29sbGVjdGlvblR5cGU6Mjc2NzExODE=","url":"https://i.seadn.io/gcs/files/fbefa1b41f7883f332c66288c3661813.gif?w=500&auto=format"},{"volume":"294.050496678000001793","floorPrice":"0.5","numOfSales":"630.000000000000000000","numOwners":"7594","volumeChange":"0.06530472954521245","totalSupply":"21279","name":"Lil Pudgys","id":"Q29sbGVjdGlvblR5cGU6MzgyNjM2NQ==","url":"https://i.seadn.io/gae/s4Td3KYsUlCblO6lQKAGAWdKwsCuumcxYpebM_YL-Pex-BP886JYAWjKBLeB5StNopAAD6kVx3QHqWm9AmudXyCaCZszHbt8SdteEQ?w=500&auto=format"},{"floorPrice":"0.639","volume":"1145.247459439957765426","numOfSales":"1766.000000000000000000","numOwners":"4986","volumeChange":"2.6710818974443336","totalSupply":"14336","name":"Azuki Elementals","id":"Q29sbGVjdGlvblR5cGU6MjcyNjM0NDA=","url":"https://i.seadn.io/gcs/files/bbaf43ee4a02d5affb7e8fc186d0bdb5.png?w=500&auto=format"},{"numOfSales":"2258.000000000000000000","floorPrice":"0.309450001","volume":"591.330718076782318349","numOwners":"1555","volumeChange":"6.2724273117971014","totalSupply":"5555","name":"Balthazar raW Pass","id":"Q29sbGVjdGlvblR5cGU6MzA4NTcxNzg=","url":"https://i.seadn.io/s/raw/files/e6249eb3ab5375845e4e69b34d76e9b2.png?w=500&auto=format"},{"numOfSales":"332.000000000000000000","volume":"314.227979796900399379","floorPrice":"0.95","numOwners":"2725","volumeChange":"0.08015477410088169","totalSupply":"11911","name":"Pixelmon - Generation 1","id":"Q29sbGVjdGlvblR5cGU6Njk0NTc1Nw==","url":"https://i.seadn.io/gcs/files/9b9979a9e40659c788d66fd2ed2749e3.png?w=500&auto=format"},{"volume":"410.586324900000022353","numOfSales":"178.000000000000000000","floorPrice":"2.07","numOwners":"2953","volumeChange":"1.037207479315057","totalSupply":"9500","name":"OnChainMonkey","id":"Q29sbGVjdGlvblR5cGU6MTUzMTc4OQ==","url":"https://i.seadn.io/gcs/files/9e95b0ff4591b3bc5da1a0bf78d03088.gif?w=500&auto=format"},{"numOfSales":"165.000000000000000000","floorPrice":"0.27","volume":"46.179456999999999312","numOwners":"3388","volumeChange":"0.12760414760927918","totalSupply":"9999","name":"a KID called BEAST","id":"Q29sbGVjdGlvblR5cGU6MjI3MzM5NjE=","url":"https://i.seadn.io/gcs/files/48e81fed9fa93c77c004f8013c6cf268.png?w=500&auto=format"},{"floorPrice":"0.12","numOfSales":"1288.000000000000000000","volume":"148.277005912123655662","numOwners":"1788","volumeChange":"584.7033278959033","totalSupply":"7070","name":"Binary: DEX","id":"Q29sbGVjdGlvblR5cGU6MjM4MDk0NjU=","url":"https://i.seadn.io/gcs/files/39bce329ecb85bb34f792ba9ca9acc3b.gif?w=500&auto=format"},{"floorPrice":"0.017","volume":"5.124321989999991445","numOfSales":"254.000000000000000000","numOwners":"2200","volumeChange":"50.70859727547922","totalSupply":"7777","name":"Kandyland","id":"Q29sbGVjdGlvblR5cGU6MjQ2MTIxNTQ=","url":"https://i.seadn.io/gcs/files/03d5a20b69810eac5fe758fc832e8705.png?w=500&auto=format"},{"numOfSales":"193.000000000000000000","volume":"475.323747999999909553","floorPrice":"3.3","numOwners":"130","volumeChange":"475.3237479999999","totalSupply":"200","name":"Signature by Jack Butcher","id":"Q29sbGVjdGlvblR5cGU6MzA5OTk1NjM=","url":"https://i.seadn.io/s/raw/files/beee672d9f049627cac8d5856e2cf185.png?w=500&auto=format"},{"numOfSales":"199.000000000000000000","floorPrice":"0.082","volume":"29.164860000000018658","numOwners":"5024","volumeChange":"0.786387131825776","totalSupply":"31","name":"My Curio Cards","id":"Q29sbGVjdGlvblR5cGU6MzEyNjU5","url":"https://i.seadn.io/gae/xNW1W9O2CYUNGS2GeHqv9yHw-wLdSb9uVoc51TL5GSp8yvC2en45pqp5zYFHhRGHZpgHJdagD2QELXwpu01frltG7Nl055aVqDTDSg?w=500&auto=format"},{"volume":"52.417497999999916658","numOfSales":"272.000000000000000000","floorPrice":"0.195","numOwners":"1051","volumeChange":"3.0647274773339053","totalSupply":"9999","name":"Ordinal Kubz","id":"Q29sbGVjdGlvblR5cGU6MjM3ODk0Mjk=","url":"https://i.seadn.io/gcs/files/f1273e4adc887cec40bb92952ca047d2.gif?w=500&auto=format"},{"floorPrice":"0.0058","numOfSales":"1275.000000000000000000","volume":"10.31977537743995299","numOwners":"2310","volumeChange":"10.319775377439953","totalSupply":"9995","name":"Fatzuki","id":"Q29sbGVjdGlvblR5cGU6Mjc1NTg4MDU=","url":"https://i.seadn.io/gcs/files/a1841e14e7d32f3cd2e172034c80451f.png?w=500&auto=format"},{"floorPrice":"0.1468","volume":"41.226927991000032137","numOfSales":"215.000000000000000000","numOwners":"6666","volumeChange":"0.4247604470689398","totalSupply":"15787","name":"Otherside Vessels","id":"Q29sbGVjdGlvblR5cGU6MjQ1ODI5ODc=","url":"https://i.seadn.io/gcs/files/8646d6116bb3f59822dc98f108d61f18.png?w=500&auto=format"},{"numOfSales":"154.000000000000000000","volume":"19.736890990000006241","floorPrice":"0.13","numOwners":"676","volumeChange":"1.0959841350871062","totalSupply":"3433","name":"Delabs Adventure Pass Official","id":"Q29sbGVjdGlvblR5cGU6MjQ1OTUyMDU=","url":"https://i.seadn.io/gcs/files/b74fe2d9830851a8970b8ac63a4479e1.png?w=500&auto=format"},{"volume":"152.699718232999970269","numOfSales":"348.000000000000000000","floorPrice":"0.478","numOwners":"1936","volumeChange":"0.12399993609064898","totalSupply":"9997","name":"Sappy Seals","id":"Q29sbGVjdGlvblR5cGU6MTI0ODU1Mw==","url":"https://i.seadn.io/gcs/files/11570389cac190891fea96fe285cbf01.png?w=500&auto=format"},{"floorPrice":"1.5199","numOfSales":"864.000000000000000000","volume":"1358.809045353723831795","numOwners":"9650","volumeChange":"0.8657115870427081","totalSupply":"19517","name":"CLONE X - X TAKASHI MURAKAMI","id":"Q29sbGVjdGlvblR5cGU6MzU2OTMyMg==","url":"https://i.seadn.io/gae/XN0XuD8Uh3jyRWNtPTFeXJg_ht8m5ofDx6aHklOiy4amhFuWUa0JaR6It49AH8tlnYS386Q0TW_-Lmedn0UET_ko1a3CbJGeu5iHMg?w=500&auto=format"},{"numOfSales":"182.000000000000000000","floorPrice":"0.89","volume":"159.813447888000155217","numOwners":"2069","volumeChange":"0.31722829929887214","totalSupply":"7843","name":"Kanpai Pandas","id":"Q29sbGVjdGlvblR5cGU6MTM3Mjg2Mjc=","url":"https://i.seadn.io/gcs/files/74096ecd2c3119eca2bf0f59a3921455.gif?w=500&auto=format"},{"floorPrice":"0.012999","numOfSales":"261.000000000000000000","volume":"2.882766999999984758","numOwners":"5191","volumeChange":"0.964674572343749","totalSupply":"29959","name":"MERGE VV","id":"Q29sbGVjdGlvblR5cGU6MjA0MTQ2NzY=","url":"https://openseauserdata.com/files/063c6b80d3579c55dab5e8810be458d5.svg"},{"numOfSales":"185.000000000000000000","floorPrice":"0.0589","volume":"15.094645483389012242","numOwners":"850","volumeChange":"-0.07418252639025188","totalSupply":"5619","name":"Mintify Genesis","id":"Q29sbGVjdGlvblR5cGU6MjgwNzgxNzk=","url":"https://i.seadn.io/gcs/files/2a2daa1fb60cd94fd629cc0c68e4a3ca.png?w=500&auto=format"},{"floorPrice":"0.144","volume":"387.367600221997008703","numOfSales":"2134.000000000000000000","numOwners":"503","volumeChange":"-0.30449232848154373","totalSupply":"1612","name":"Sofa Maker","id":"Q29sbGVjdGlvblR5cGU6MzA5NjkyNDI=","url":"https://i.seadn.io/s/raw/files/27739eb74ab600dcecae22b22115c1bc.gif?w=500&auto=format"},{"numOfSales":"2286.000000000000000000","floorPrice":"0.674","volume":"1216.193001678912651187","numOwners":"1861","volumeChange":"5.495917151537454","totalSupply":"5555","name":"BlockGames Dice","id":"Q29sbGVjdGlvblR5cGU6MzA2NzkxODY=","url":"https://i.seadn.io/s/raw/files/2977805d19a49a608d5387ac4bdc24e9.png?w=500&auto=format"},{"numOfSales":"374.000000000000000000","volume":"274.578267799910747726","floorPrice":"0.63","numOwners":"15902","volumeChange":"-0.3099130722078947","totalSupply":"47572","name":"Otherdeed for Otherside","id":"Q29sbGVjdGlvblR5cGU6MTQwNzcyNTU=","url":"https://i.seadn.io/gae/yIm-M5-BpSDdTEIJRt5D6xphizhIdozXjqSITgK4phWq7MmAU3qE7Nw7POGCiPGyhtJ3ZFP8iJ29TFl-RLcGBWX5qI4-ZcnCPcsY4zI?w=500&auto=format"},{"floorPrice":"0.97","volume":"417.334611779987881164","numOfSales":"420.000000000000000000","numOwners":"5599","volumeChange":"3.6493025209208025","totalSupply":"9965","name":"Cool Cats","id":"Q29sbGVjdGlvblR5cGU6NzQ2NzAw","url":"https://i.seadn.io/gae/LIov33kogXOK4XZd2ESj29sqm_Hww5JSdO7AFn5wjt8xgnJJ0UpNV9yITqxra3s_LMEW1AnnrgOVB_hDpjJRA1uF4skI5Sdi_9rULi8?w=500&auto=format"},{"volume":"137.175358886442040784","numOfSales":"221.000000000000000000","floorPrice":"0.669999","numOwners":"4283","volumeChange":"6.227638040751814","totalSupply":"10417","name":"Impostors Genesis Aliens","id":"Q29sbGVjdGlvblR5cGU6OTA3NDA4OQ==","url":"https://i.seadn.io/s/raw/files/ed928558c4778f80e6096904e0814c2c.png?w=500&auto=format"},{"numOfSales":"174.000000000000000000","volume":"27.614257000000016262","floorPrice":"0.136998","numOwners":"3441","volumeChange":"0.26867915575503526","totalSupply":"8887","name":"Ninja Squad Official","id":"Q29sbGVjdGlvblR5cGU6MjkxMTAwNw==","url":"https://i.seadn.io/gae/xVyUwQMXGvCha3V8UQ1laIx5tfwpmR76Bu1L0oaNKHfxz0FS_t5Y6wRlXBTFqZNlGb0ixL4_TSifMtjQUgv25ZPuTHaFVNitFGf4Dw?w=500&auto=format"},{"floorPrice":"0.059299","numOfSales":"328.000000000000000000","volume":"20.750355799999997686","numOwners":"2921","volumeChange":"-0.687844390146731","totalSupply":"10000","name":"TrekkiNFT","id":"Q29sbGVjdGlvblR5cGU6MzA4ODkwNjc=","url":"https://i.seadn.io/s/raw/files/2ba801aa5b5ea5cd7ec85f4bc7e351bd.png?w=500&auto=format"},{"floorPrice":"0.512","volume":"204.226516800000354124","numOfSales":"431.000000000000000000","numOwners":"2376","volumeChange":"-0.009991059184043269","totalSupply":"9172","name":"Redacted Remilio Babies","id":"Q29sbGVjdGlvblR5cGU6MTkxNjEwMDY=","url":"https://i.seadn.io/gcs/files/9d6168e731afd02d5e878eb03876cfd4.gif?w=500&auto=format"},{"volume":"84.312292719095438542","floorPrice":"0.552763819095477387","numOfSales":"192.000000000000000000","numOwners":"3308","volumeChange":"1.9503810464884461","totalSupply":"10420","name":"Treeverse Plots","id":"Q29sbGVjdGlvblR5cGU6ODQ4MTky","url":"https://i.seadn.io/gcs/files/13d771dac2ff1944a8446ddeb5f32f44.jpg?w=500&auto=format"},{"floorPrice":"0.309","volume":"296.497075145600661017","numOfSales":"948.000000000000000000","numOwners":"1808","volumeChange":"7.269141805907285","totalSupply":"5700","name":"Checks - VV Originals","id":"Q29sbGVjdGlvblR5cGU6MjM1MDAxOTI=","url":"https://i.seadn.io/gcs/files/86ce94827a5e991b18f382577fd00281.png?w=500&auto=format"},{"volume":"157.272640800000004901","numOfSales":"378.000000000000000000","floorPrice":"0.42","numOwners":"1864","volumeChange":"6.684397314830241","totalSupply":"9999","name":"Kubz","id":"Q29sbGVjdGlvblR5cGU6MjI2ODUyNjU=","url":"https://i.seadn.io/gcs/files/820d812a78a8d20c544aba019feb4db2.png?w=500&auto=format"},{"volume":"142.122598521621682721","numOfSales":"181.000000000000000000","floorPrice":"0.819","numOwners":"2127","volumeChange":"-0.6580249202104148","totalSupply":"11001","name":"Parallel Avatars","id":"Q29sbGVjdGlvblR5cGU6MjczNzMyNTI=","url":"https://i.seadn.io/gcs/files/f77f0f2cc27dd427c69c68e81bfb0b97.gif?w=500&auto=format"},{"numOfSales":"1639.000000000000000000","volume":"5351.288351586981661967","floorPrice":"3.4799","numOwners":"2525","volumeChange":"1.5171443887913694","totalSupply":"8947","name":"DeGods","id":"Q29sbGVjdGlvblR5cGU6MjQ0MTQyNjg=","url":"https://i.seadn.io/gcs/files/c6cb0b1d6f2ab61c0efacf00e62e2230.jpg?w=500&auto=format"},{"volume":"164.405772798900045473","floorPrice":"0.26","numOfSales":"725.000000000000000000","numOwners":"3036","volumeChange":"0.15150119449698887","totalSupply":"10000","name":"Shrapnel Operators Collection","id":"Q29sbGVjdGlvblR5cGU6MTYyMzE3NTA=","url":"https://i.seadn.io/gae/N-0Ykz_InP31IMCnBV4gXAjPfXbkoOmENXGZjKRdK6mo2dO-hRcAHHPyQ-oBLcQMgWwzmh06GHeJ5U0yib3IDE9ekrvVc_-qlOWK?w=500&auto=format"},{"volume":"8474.373880399003610364","floorPrice":"5.758","numOfSales":"1528.000000000000000000","numOwners":"11355","volumeChange":"1.2191719933530085","totalSupply":"19485","name":"Mutant Ape Yacht Club","id":"Q29sbGVjdGlvblR5cGU6MTE2Njc5NA==","url":"https://i.seadn.io/gae/lHexKRMpw-aoSyB1WdFBff5yfANLReFxHzt1DOj_sg7mS14yARpuvYcUtsyyx-Nkpk6WTcUPFoG53VnLJezYi8hAs0OxNZwlw6Y-dmI?w=500&auto=format"},{"floorPrice":"1.7998","volume":"1471.923496184761233962","numOfSales":"845.000000000000000000","numOwners":"5114","volumeChange":"4.084475529406484","totalSupply":"9602","name":"Bored Ape Kennel Club","id":"Q29sbGVjdGlvblR5cGU6NzI1MTc5","url":"https://i.seadn.io/gcs/files/c4dfc6be4d9c5d4f073de2efe181416a.jpg?w=500&auto=format"},{"volume":"30.29328180400001358","floorPrice":"0.1569","numOfSales":"225.000000000000000000","numOwners":"1272","volumeChange":"0.18328369602708583","totalSupply":"4812","name":"Ether","id":"Q29sbGVjdGlvblR5cGU6Mjc2NDIxODM=","url":"https://i.seadn.io/s/raw/files/2ec7df3710428cdd6215261b6f3bfef0.jpg?w=500&auto=format"},{"floorPrice":"0.3549","volume":"321.479470078896270024","numOfSales":"940.000000000000000000","numOwners":"7871","volumeChange":"0.9934754490133682","totalSupply":"19950","name":"BEANZ Official","id":"Q29sbGVjdGlvblR5cGU6MTI1MTYzNjQ=","url":"https://i.seadn.io/gae/_R4fuC4QGYd14-KwX2bD1wf-AWjDF2VMabfqWFJhIgiN2FnAUpnD5PLdJORrhQ8gly7KcjhQZZpuzYVPF7CDSzsqmDh97z84j2On?w=500&auto=format"},{"numOfSales":"521.000000000000000000","volume":"73.520922428888908939","floorPrice":"0.049","numOwners":"10404","volumeChange":"10.933671740637893","totalSupply":"11","name":"Inhabitants: United Planets","id":"Q29sbGVjdGlvblR5cGU6MTkzNTYyOQ==","url":"https://i.seadn.io/gcs/files/273aea7e405f51fb0da17ab7fd568f18.png?w=500&auto=format"},{"numOfSales":"227.000000000000000000","volume":"13.881015080701985198","floorPrice":"0.00019","numOwners":"42338","volumeChange":"-0.260139101765351","totalSupply":"650","name":"Town Star","id":"Q29sbGVjdGlvblR5cGU6MTA1NjM=","url":"https://i.seadn.io/gcs/files/ad2ed32f6e82fb823618ea282d4a7715.png?w=500&auto=format"},{"volume":"670.255795410256837386","floorPrice":"2.297999","numOfSales":"354.000000000000000000","numOwners":"2090","volumeChange":"2.2028416935186677","totalSupply":"9154","name":"Creepz by OVERLORD","id":"Q29sbGVjdGlvblR5cGU6NDUyMDk3OA==","url":"https://i.seadn.io/gcs/files/13f3b6e7226f54d739ad8c3ed838802b.png?w=500&auto=format"},{"numOfSales":"372.000000000000000000","volume":"835.046527959001423369","floorPrice":"2.49","numOwners":"3461","volumeChange":"0.39674189310481933","totalSupply":"9732","name":"Milady Maker","id":"Q29sbGVjdGlvblR5cGU6MTA1NzQ5Mw==","url":"https://i.seadn.io/gae/a_frplnavZA9g4vN3SexO5rrtaBX_cBTaJYcgrPtwQIqPhzgzUendQxiwUdr51CGPE2QyPEa1DHnkW1wLrHAv5DgfC3BP-CWpFq6BA?w=500&auto=format"},{"volume":"145.443980999900304596","numOfSales":"210.000000000000000000","floorPrice":"0.699899","numOwners":"5679","volumeChange":"0.2916798097224086","totalSupply":"10019","name":"mfers","id":"Q29sbGVjdGlvblR5cGU6MzE2OTU0NQ==","url":"https://i.seadn.io/gae/J2iIgy5_gmA8IS6sXGKGZeFVZwhldQylk7w7fLepTE9S7ICPCn_dlo8kypX8Ju0N6wvLVOKsbP_7bNGd8cpKmWhFQmqMXOC8q2sOdqw?w=500&auto=format"},{"numOfSales":"2450.000000000000000000","floorPrice":"0.1077","volume":"308.557977815800597909","numOwners":"1075","volumeChange":"308.5579778158006","totalSupply":"3944","name":"Sofa Vision","id":"Q29sbGVjdGlvblR5cGU6MzEwNDY0MTY=","url":"https://i.seadn.io/s/raw/files/27739eb74ab600dcecae22b22115c1bc.gif?w=500&auto=format"},{"numOfSales":"294.000000000000000000","volume":"76.473253302000017584","floorPrice":"0.00145","numOwners":"833835","volumeChange":"-0.20840139128857013","totalSupply":"3077611","name":"ENS: Ethereum Name Service","id":"Q29sbGVjdGlvblR5cGU6MzA3Mg==","url":"https://i.seadn.io/gae/0cOqWoYA7xL9CkUjGlxsjreSYBdrUBE0c6EO1COG4XE8UeP-Z30ckqUNiL872zHQHQU5MUNMNhfDpyXIP17hRSC5HQ?w=500&auto=format"},{"numOfSales":"345.000000000000000000","volume":"27.059282599799903579","floorPrice":"0.0942","numOwners":"2590","volumeChange":"1.4267742355660171","totalSupply":"10000","name":"KPR","id":"Q29sbGVjdGlvblR5cGU6MjE5NDI3Mzg=","url":"https://i.seadn.io/gcs/files/845c91b06d1311576e9e7c39bae69244.png?w=500&auto=format"},{"numOfSales":"1243.000000000000000000","volume":"2638.630315478008924401","floorPrice":"2.1379","numOwners":"6038","volumeChange":"1.642669977366203","totalSupply":"10000","name":"Moonbirds","id":"Q29sbGVjdGlvblR5cGU6MTMzNjAzMjU=","url":"https://i.seadn.io/gcs/files/4bce6187fea476154b311dafaf327c89.png?w=500&auto=format"},{"floorPrice":"0.08","volume":"24.98678080000000179","numOfSales":"174.000000000000000000","numOwners":"2832","volumeChange":"0.4800588237768005","totalSupply":"9996","name":"Genuine Undead","id":"Q29sbGVjdGlvblR5cGU6MTYzOTI1NDg=","url":"https://i.seadn.io/gcs/files/1eb8d685d4e404c9b1177dfe14c2c9e0.png?w=500&auto=format"},{"volume":"1687.310888906973559642","floorPrice":"0.7299","numOfSales":"2847.000000000000000000","numOwners":"3287","volumeChange":"9.755759229408495","totalSupply":"10087","name":"Yogapetz","id":"Q29sbGVjdGlvblR5cGU6Mjk3ODg3Mjg=","url":"https://i.seadn.io/gcs/files/245b32abea15dd17e8855013538fd136.png?w=500&auto=format"},{"volume":"59.719701244162784803","floorPrice":"0.23999","numOfSales":"205.000000000000000000","numOwners":"24698","volumeChange":"-0.2053472789676938","totalSupply":"165720","name":"The Sandbox","id":"Q29sbGVjdGlvblR5cGU6NTYwNA==","url":"https://i.seadn.io/gae/SXH8tW1siikB80rwCRnjm1a5xM_MwTg9Xl9Db6mioIk9HIlDM09pVoSR7GKJgS6ulSUpgW9BDtMk_ePX_NKgO9A?w=500&auto=format"},{"floorPrice":"0.634","volume":"139.750469796869992933","numOfSales":"313.000000000000000000","numOwners":"1885","volumeChange":"1.4615638844377923","totalSupply":"5414","name":"Checks - VV Edition","id":"Q29sbGVjdGlvblR5cGU6MjI4MDE0MTY=","url":"https://i.seadn.io/gcs/files/864dce41a43d14e0c083ad9434cb8261.png?w=500&auto=format"},{"numOfSales":"1358.000000000000000000","volume":"28.963096851049954239","floorPrice":"0.037","numOwners":"347","volumeChange":"28.963096851049954","totalSupply":"1000","name":"Together","id":"Q29sbGVjdGlvblR5cGU6MzEwNTYyNTA=","url":"https://i.seadn.io/s/raw/files/c4f91391ceee533a437e5b04a28e943d.gif?w=500&auto=format"},{"numOfSales":"209.000000000000000000","volume":"887.268408000010254","floorPrice":"4.339","numOwners":"3988","volumeChange":"-0.6247148064271166","totalSupply":"9999","name":"The Captainz","id":"Q29sbGVjdGlvblR5cGU6MjI4NTYwMzY=","url":"https://i.seadn.io/gcs/files/6df4d75778066bce740050615bc84e21.png?w=500&auto=format"},{"floorPrice":"0.0000099","volume":"5.682891376104254988","numOfSales":"22921.000000000000000000","numOwners":"3147","volumeChange":"1.2411291705059126","totalSupply":"226","name":"Pirate Nation - Items","id":"Q29sbGVjdGlvblR5cGU6MzAzNDIzMTU=","url":"https://i.seadn.io/gcs/files/06a07158febfe5dded5c2e13e4cac214.gif?w=500&auto=format"},{"volume":"467.171929770680321781","floorPrice":"0.4449","numOfSales":"922.000000000000000000","numOwners":"4076","volumeChange":"-0.09166116934084635","totalSupply":"16000","name":"Opepen Edition","id":"Q29sbGVjdGlvblR5cGU6MjI4OTYwNTQ=","url":"https://i.seadn.io/gcs/files/b1c9ed2e584b4f6e418bf1ca15311844.jpg?w=500&auto=format"},{"numOfSales":"154.000000000000000000","volume":"378.102778888887883113","floorPrice":"2.2","numOwners":"1604","volumeChange":"0.792475368335754","totalSupply":"9999","name":"HYTOPIA Worlds","id":"Q29sbGVjdGlvblR5cGU6MjU5MzgzMjQ=","url":"https://i.seadn.io/gcs/files/b14329da267669950c65d95b030a305f.png?w=500&auto=format"},{"floorPrice":"3.25","volume":"1522.893460174601159451","numOfSales":"526.000000000000000000","numOwners":"1043","volumeChange":"5.157091475719905","totalSupply":"3332","name":"The Grapes","id":"Q29sbGVjdGlvblR5cGU6MjYzNjQxMTM=","url":"https://i.seadn.io/gcs/files/39d91be7a3328d2c4655cdf39a08dc71.gif?w=500&auto=format"},{"numOfSales":"377.000000000000000000","volume":"55.150811879989952047","floorPrice":"0.033","numOwners":"8869","volumeChange":"0.07946659155506036","totalSupply":"170","name":"The Memes by 6529","id":"Q29sbGVjdGlvblR5cGU6MTYzOTE4OTM=","url":"https://i.seadn.io/gcs/files/8573c42207ea4d7dc1bb6ed5c0b01243.jpg?w=500&auto=format"},{"volume":"3055.622183999791559472","floorPrice":"6.44","numOfSales":"511.000000000000000000","numOwners":"4415","volumeChange":"0.9060168288984604","totalSupply":"8888","name":"Pudgy Penguins","id":"Q29sbGVjdGlvblR5cGU6ODA5OTEy","url":"https://i.seadn.io/gae/yNi-XdGxsgQCPpqSio4o31ygAV6wURdIdInWRcFIl46UjUQ1eV7BEndGe8L661OoG-clRi7EgInLX4LPu9Jfw4fq0bnVYHqg7RFi?w=500&auto=format"},{"numOfSales":"393.000000000000000000","floorPrice":"6.25","volume":"2355.154824999995071266","numOwners":"4197","volumeChange":"0.9079535004532936","totalSupply":"10000","name":"Azuki","id":"Q29sbGVjdGlvblR5cGU6NDc2MzQ0Ng==","url":"https://i.seadn.io/gae/H8jOCJuQokNqGBpkBN5wk1oZwO7LM8bNnrHCaekV2nKjnCqw6UB5oaH8XyNeBDj6bA_n1mjejzhFQUP3O1NfjFLHr3FOaeHcTOOT?w=500&auto=format"},{"floorPrice":"0.285","numOfSales":"200.000000000000000000","volume":"112.163996999000019628","numOwners":"13372","volumeChange":"0.1773155039273052","totalSupply":"52427","name":"Otherdeed Expanded","id":"Q29sbGVjdGlvblR5cGU6MjQ1ODI5NTU=","url":"https://i.seadn.io/gcs/files/9583ab4792a83cd81d5075b59514a34a.png?w=500&auto=format"},{"volume":"18.802935900000040448","floorPrice":"0.02222","numOfSales":"1241.000000000000000000","numOwners":"188","volumeChange":"1.0327838525323048","totalSupply":"13","name":"THE WHITE RABBIT","id":"Q29sbGVjdGlvblR5cGU6MzEwMDA3NDQ=","url":"https://i.seadn.io/s/raw/files/db9fed8cca881d54c9edb49320b67910.png?w=500&auto=format"},{"volume":"439.703359999999918273","floorPrice":"3.09","numOfSales":"159.000000000000000000","numOwners":"1122","volumeChange":"0.9214840004402115","totalSupply":"3045","name":"Neo Tokyo Outer Citizens","id":"Q29sbGVjdGlvblR5cGU6MjY4NzgyNzQ=","url":"https://i.seadn.io/gcs/files/827bae7c89a17abddfd7b831461a3213.png?w=500&auto=format"},{"numOfSales":"166.000000000000000000","floorPrice":"0.008998","volume":"1.449307799999999702","numOwners":"1787","volumeChange":"0.10154129826580244","totalSupply":"9664","name":"Deadmigos","id":"Q29sbGVjdGlvblR5cGU6MzA3MDQxMzk=","url":"https://i.seadn.io/s/raw/files/dd6ded45e462561cbdebcc5500452a18.png?w=500&auto=format"}]