[{"floorPrice":"14.99","volume":"0.03538230127638064","numOwners":"110","volumeChange":"0.4496","totalSupply":"241","name":"Anime Warrior","id":"747520513872703488","url":"https://public.nftstatic.com/static/nft/res/nft-cex/S3/1699442961647_bapqxbfaxc8nrt3wkvlvcxllgdleokgy.gif"},{"floorPrice":"0.18","volume":"0.010918477189435108","numOwners":"29230","volumeChange":"1.0115","totalSupply":"144000","name":"Alpine Race Collectibles","id":"692959699477970944","url":"https://public.nftstatic.com/static/nft/res/c5a578c386684132a36d17e5c3735df0.png"},{"floorPrice":"15.0","volume":"0.023304644256287123","numOwners":"57","volumeChange":"0.5354","totalSupply":"150","name":"Bitcoin NFT -  BTC XRP SHIB DOGE","id":"708514458696572928","url":"https://public.nftstatic.com/static/nft/res/nft-cex/S3/1683691361454_tufg4hh65npe021cpfgexjupq4wsbvl3.gif"},{"floorPrice":"9.99","volume":"0.015474883103753317","numOwners":"59","volumeChange":"-0.13949999999999999","totalSupply":"172","name":"Bitcoin Holders","id":"748922437476036608","url":"https://public.nftstatic.com/static/nft/res/nft-cex/S3/1700568513419_cyof2jo08caex7durmpi923sp8rk1f4z.gif"},{"floorPrice":"6.8","volume":"0.014618848729938079","numOwners":"70","volumeChange":"-0.3691","totalSupply":"223","name":"Homie Metaverse","id":"746406346941050880","url":"https://public.nftstatic.com/static/nft/res/nft-cex/S3/1698945075043_gzi3o57k2181mf2tc0bh2ukug9kqjlah.gif"},{"floorPrice":"5.99","volume":"0.013598072791608747","numOwners":"107","volumeChange":"0.2371","totalSupply":"306","name":"Metaverse NFT Collection","id":"752553272268472320","url":"https://public.nftstatic.com/static/nft/res/nft-cex/S3/1694555455762_x9bwyzzo5kqvrnx7vqkiq2kai59c3d7t.gif"},{"floorPrice":"5.1","volume":"0.018280351952483256","numOwners":"327","volumeChange":"-0.049800000000000004","totalSupply":"603","name":"Rose Collection","id":"668759428913696768","url":"https://public.nftstatic.com/static/nft/res/nft-cex/S3/1686313208695_dom4t3byesa95h118zn520ugcd0pdplj.gif"},{"floorPrice":"0.18","volume":"0.0023926999873625683","numOwners":"0","volumeChange":"-0.8471","totalSupply":"10004","name":"🙀 Voodoo Kitten 🙀","id":"601704584883970048","url":"https://public.nftstatic.com/static/nft/res/nft-cex/S3/1658299009140_852z65fwbcq84mbbpgdxb1wrluqme8jy.gif"},{"floorPrice":"16.8","volume":"0.010767035258435486","numOwners":"33","volumeChange":"10.3599","totalSupply":"118","name":"Ethereum NFT - ETH XRP BTC DOGE","id":"740980151981899777","url":"https://public.nftstatic.com/static/nft/res/nft-cex/S3/1694886186765_otid6l7vwu0hrczm0ufptd7oifg5rbw0.gif"},{"floorPrice":"800.82","volume":"6.411608281309238","numOwners":"4146","volumeChange":"0.3515","totalSupply":"16000","name":"Opepen Edition","id":"668545431091167233","url":"https://public.nftstatic.com/static/nft/res/nft-cex/S3/1674158452400_vx3wp10xif320ent425wm1a378f7hr77.png"},{"floorPrice":"8.7","volume":"0.006676734487552131","numOwners":"121","volumeChange":"33.0858","totalSupply":"816","name":"MOTORCYCLE BABIES","id":"674576679284477953","url":"https://public.nftstatic.com/static/nft/res/nft-cex/S3/1694191221302_3400emcjpf0me4ejxp4s1apipdkzes9d.gif"},{"floorPrice":"0.47","volume":"0.00991631492480728","numOwners":"15396","volumeChange":"1.4385","totalSupply":"50000","name":"The CR7 ForeverZone Box","id":"407802751394464768","url":"https://public.nftstatic.com/static/nft/res/c5c23ecbddc545348090905147dfb4ad.png"},{"floorPrice":"10126.37","volume":"53.12822826235308","numOwners":"11542","volumeChange":"-0.33509999999999995","totalSupply":"19485","name":"Mutant Ape Yacht Club","id":"505303452945186817","url":"https://public.nftstatic.com/static/nft/res/2c66a6e10df04bbea3eff518e06f8d73.jpeg"},{"floorPrice":"3.88","volume":"0.0064978263616833065","numOwners":"35","volumeChange":"0.0","totalSupply":"148","name":"GODDESS NFT","id":"664413273701097473","url":"https://public.nftstatic.com/static/nft/res/nft-cex/S3/1673173053312_7au87thgo1o5ccuhr1zg4vj039j9efmy.png"},{"floorPrice":"6086.23","volume":"26.409959886263113","numOwners":"2536","volumeChange":"-0.2829","totalSupply":"8683","name":"DeGods","id":"694369170047053825","url":"https://public.nftstatic.com/static/nft/res/nft-cex/S3/1680315311520_bbkd4ll4i5ylykbam34twi0omc736x8p.png"},{"floorPrice":"15.0","volume":"0.00424371919625932","numOwners":"40","volumeChange":"-0.6313","totalSupply":"280","name":"Metaverse Ape Yacht Club","id":"753770820135309313","url":"https://public.nftstatic.com/static/nft/res/nft-cex/S3/1694477256483_uhqm3lxlpji6zybii8m38s1ktmsembnu.gif"},{"floorPrice":"15.29","volume":"0.08728093011500064","numOwners":"3162","volumeChange":"1.8771","totalSupply":"25115","name":"The Syphon","id":"189627778021383168","url":"https://public.nftstatic.com/static/nft/res/b5a02a493f354d109f1e08eff0b69e79.jpeg"},{"floorPrice":"860.68","volume":"3.2601113585239485","numOwners":"7574","volumeChange":"0.0139","totalSupply":"21278","name":"Lil Pudgys","id":"528399448512405505","url":"https://public.nftstatic.com/static/nft/res/448fce1fabc24a46b4a1cba661fec292.png"},{"floorPrice":"1511.55","volume":"4.913687913559965","numOwners":"2135","volumeChange":"1.0146","totalSupply":"11001","name":"Parallel Avatars","id":"729456622577106945","url":"https://public.nftstatic.com/static/nft/res/nft-extdata-loader/S3/1689566900605_frdc23351j48m7gts0o4hy7kymy1z59x.jpg"},{"floorPrice":"15.79","volume":"0.09294606343990902","numOwners":"6942","volumeChange":"2.1743","totalSupply":"40250","name":"The Infinity Vault","id":"140242452236967936","url":"https://public.nftstatic.com/static/nft/res/1c761fc2d4fb49c39f678ae6f0cf816f.jpeg"},{"floorPrice":"0.0","volume":"0.35503501200556054","numOwners":"0","volumeChange":"8.902000000000001","totalSupply":"9795","name":"8liens NFT","id":"641536435656134656","url":"https://public.nftstatic.com/static/nft/res/nft-cex/S3/1667877683893_teh78l5o4xsx7e89xn6xvpuwcyk746eq.gif"},{"floorPrice":"870.89","volume":"2.938303423480349","numOwners":"600","volumeChange":"0.8633","totalSupply":"1000","name":"Velocity Series: Velocity Pass","id":"739705404534157313","url":"https://public.nftstatic.com/static/nft/res/nft-extdata-loader/S3/1691124371107_scjwjpzl08fxtxxprfehdxhcm4pkars2.jpg"},{"floorPrice":"659.79","volume":"2.0165466611904463","numOwners":"7886","volumeChange":"-0.7228","totalSupply":"19950","name":"BEANZ Official","id":"641881145226350593","url":"https://public.nftstatic.com/static/nft/res/nft-cex/S3/1667801191325_338ee699dzk7uo3meez6rkttidw9tvfc.png"},{"floorPrice":"1141.17","volume":"4.082595139011753","numOwners":"3073","volumeChange":"0.1318","totalSupply":"100000","name":"Otherdeed for Otherside","id":"641881071684722689","url":"https://public.nftstatic.com/static/nft/res/nft-cex/S3/1667801173679_6osf0fmr4zgqsgotq5zt40pzdm8njn3g.png"},{"floorPrice":"4004.1","volume":"11.992435305193986","numOwners":"6146","volumeChange":"0.47009999999999996","totalSupply":"10000","name":"Moonbirds","id":"569066442241241089","url":"https://public.nftstatic.com/static/nft/res/5966121f53a842f793d02d24cf196e1c.png"},{"floorPrice":"3.0","volume":"0.00400214204473651","numOwners":"25","volumeChange":"0.0","totalSupply":"128","name":"RARE CLONES","id":"669287355745329152","url":"https://public.nftstatic.com/static/nft/res/nft-cex/S3/1679525455742_in7uvzgweciyd0aclpayuqzlf0nixi20.gif"},{"floorPrice":"1227.66","volume":"3.8400058713509417","numOwners":"4708","volumeChange":"-0.63","totalSupply":"14234","name":"Azuki Elementals","id":"726319061462085633","url":"https://public.nftstatic.com/static/nft/res/nft-extdata-loader/S3/1687932850971_35r93kq25q763r0zvu5o5lg7id729hej.jpg"},{"floorPrice":"3023.1","volume":"8.105740336787566","numOwners":"9648","volumeChange":"-0.6242","totalSupply":"19517","name":"CLONE X - X TAKASHI MURAKAMI","id":"533652760429920257","url":"https://public.nftstatic.com/static/nft/res/b8b7c6ac4743492db019ce26f7347462.jpeg"},{"floorPrice":"343.95","volume":"1.0662653677492735","numOwners":"5647","volumeChange":"-0.06280000000000001","totalSupply":"20000","name":"Nakamigos","id":"690968054768242689","url":"https://public.nftstatic.com/static/nft/res/nft-cex/S3/1679504422444_vjcv41ljfw58vjy9hkcyarbkxjus3u2d.png"},{"floorPrice":"3.89","volume":"0.0048729179830658415","numOwners":"149","volumeChange":"-0.09849999999999999","totalSupply":"890","name":"THE CAGE","id":"663845917881667584","url":"https://public.nftstatic.com/static/nft/res/nft-cex/S3/1679526788029_zfdb3xmumsw9q3x19mkwbza0zhcr9hx1.gif"},{"floorPrice":"9109.33","volume":"25.61909334133704","numOwners":"3990","volumeChange":"-0.21760000000000002","totalSupply":"9999","name":"The Captainz","id":"664106493958045697","url":"https://public.nftstatic.com/static/nft/res/nft-cex/S3/1673100127317_ftyn7zwf6v3raznvt22ayl2k1f1t6kk4.png"},{"floorPrice":"33.0","volume":"0.0721768153671174","numOwners":"45234","volumeChange":"-0.6468","totalSupply":"94757","name":"Gemesis","id":"695709251536801793","url":"https://public.nftstatic.com/static/nft/res/nft-extdata-loader/S3/1680634925214_xtb6fk14mq6we8qt87wamdypf3uxs0uy.jpg"},{"floorPrice":"58.99","volume":"0.14576515923164413","numOwners":"472","volumeChange":"0.2903","totalSupply":"10000","name":"Block Legends","id":"718120215278723072","url":"https://public.nftstatic.com/static/nft/res/6d29b3b8bc4f449ba4a6d93ba8319647.png"},{"floorPrice":"780.4","volume":"2.0693470687476303","numOwners":"2565","volumeChange":"0.09759999999999999","totalSupply":"10000","name":"Redacted Remilio Babies","id":"668643429774356481","url":"https://public.nftstatic.com/static/nft/res/nft-cex/S3/1678261197262_an96jigwq039okugxmqdh4gjlqyrz9ch.gif"},{"floorPrice":"4128.03","volume":"8.780883970049286","numOwners":"653","volumeChange":"0.1244","totalSupply":"2061","name":"Matr1x 2061","id":"679892531327184897","url":"https://public.nftstatic.com/static/nft/res/4c5089f3346940d3aa9b9fe6b0b922f2.png"},{"floorPrice":"4893.81","volume":"9.558190105522558","numOwners":"3543","volumeChange":"-0.25920000000000004","totalSupply":"10000","name":"Milady Maker","id":"640794577033273345","url":"https://public.nftstatic.com/static/nft/res/nft-cex/S3/1667874736142_4iimvwacp4r3v0khr6j8sr2tlzyxs8zr.jpg"},{"floorPrice":"11611.89","volume":"21.56136298306584","numOwners":"4435","volumeChange":"-0.3123","totalSupply":"8888","name":"Pudgy Penguins","id":"507850950909366272","url":"https://public.nftstatic.com/static/nft/res/9e9d1ca1a76847418c3a10ac13c627db.png"},{"floorPrice":"1801.85","volume":"2.827588543535954","numOwners":"1551","volumeChange":"-0.31420000000000003","totalSupply":"5664","name":"Azuki Elemental Beans","id":"726020668084563969","url":"https://public.nftstatic.com/static/nft/res/0ac510b4d43d490eb847787c7f67b4c2.jpeg"},{"floorPrice":"14.5","volume":"0.0023646404650575006","numOwners":"94","volumeChange":"-0.5238","totalSupply":"719","name":"HERO SKULLS","id":"671407666795769857","url":"https://public.nftstatic.com/static/nft/res/nft-cex/S3/1694190721954_h4xh7fnfm1niyyorzizbcsq94xxop289.gif"},{"floorPrice":"3541.43","volume":"6.42906330152913","numOwners":"2813","volumeChange":"-0.0433","totalSupply":"9999","name":"The Potatoz","id":"627028585490763776","url":"https://public.nftstatic.com/static/nft/res/b4bf0e0b2b9a406eaa4787f21a5b2706.gif"},{"floorPrice":"82.08","volume":"0.09810281814735246","numOwners":"3608","volumeChange":"1.8814","totalSupply":"37036","name":"ASM AIFA All-Stars","id":"700344797558829057","url":"https://public.nftstatic.com/static/nft/res/nft-extdata-loader/S3/1681740130406_bdnmn45q953f1tztdpnlrnptbs4ptugi.jpg"},{"floorPrice":"5.0","volume":"0.0018694995576898777","numOwners":"0","volumeChange":"-0.7915000000000001","totalSupply":"2622","name":"PRIME APE","id":"610426331564736512","url":"https://public.nftstatic.com/static/nft/res/nft-cex/S3/1662369499381_6ddhmk90crst776u8z4n1kk4rnldvibo.gif"},{"floorPrice":"6.99","volume":"0.0017870535827119928","numOwners":"201","volumeChange":"-0.7816","totalSupply":"818","name":"NEON CUTS","id":"671432400327327744","url":"https://public.nftstatic.com/static/nft/res/nft-cex/S3/1694190902316_zi85kmtk2gfkgrrvp3ghiczcz6o6aksc.gif"},{"floorPrice":"620.64","volume":"1.6294889315051182","numOwners":"12826","volumeChange":"-0.3503","totalSupply":"52349","name":"Otherdeed Expanded","id":"696173597875834881","url":"https://public.nftstatic.com/static/nft/res/nft-extdata-loader/S3/1680745570357_kwuoqkwgcwdqu2fobh7erh298y7lz43m.jpg"},{"floorPrice":"14.65","volume":"0.05125268545431569","numOwners":"4621","volumeChange":"0.43729999999999997","totalSupply":"18000","name":"The Paradox Forge","id":"121507326539875328","url":"https://public.nftstatic.com/static/nft/res/bf70e4f7d3d64d2dbc87584d5fda0c8e.jpeg"},{"floorPrice":"11185.25","volume":"17.39997760457475","numOwners":"4255","volumeChange":"-0.5243","totalSupply":"10000","name":"Azuki","id":"566536999900893185","url":"https://public.nftstatic.com/static/nft/res/303d4787c96242a1bb000136dd57f405.jpeg"},{"floorPrice":"326.13","volume":"0.48804504928598513","numOwners":"2","volumeChange":"3.0521","totalSupply":"8888","name":"Ninja Squad Official","id":"668567990451990529","url":"https://public.nftstatic.com/static/nft/res/nft-cex/S3/1674163830963_w4j853y6degimoiihixeezdzda3mqots.png"},{"floorPrice":"3924.02","volume":"5.3059258694553275","numOwners":"5620","volumeChange":"-0.7076","totalSupply":"10000","name":"Doodles","id":"533647159874920449","url":"https://public.nftstatic.com/static/nft/res/40d30afcdd6a49939e89bb124e4cf85c.jpeg"},{"floorPrice":"3223.1","volume":"4.409915104890686","numOwners":"5134","volumeChange":"-0.479","totalSupply":"9602","name":"Bored Ape Kennel Club","id":"641881108745592833","url":"https://public.nftstatic.com/static/nft/res/nft-cex/S3/1667801182515_w2evj8h6omdvfgozzfyru7oqwpfjr3tm.png"},{"floorPrice":"2686.95","volume":"3.6589149879944403","numOwners":"6615","volumeChange":"-0.7145","totalSupply":"20000","name":"Meebits","id":"620207919082143744","url":"https://public.nftstatic.com/static/nft/res/5bc971125c4640b0be2ddb6f08ee1367.png"},{"floorPrice":"1659.3","volume":"2.463595511815999","numOwners":"2719","volumeChange":"-0.5666","totalSupply":"11867","name":"Pixelmon - Generation 1","id":"657544850517258241","url":"https://public.nftstatic.com/static/nft/res/nft-cex/S3/1671538727863_qtij3ornjpwcekfcj5scq96jy0fgctoy.gif"},{"floorPrice":"749.77","volume":"0.8588616864653104","numOwners":"2035","volumeChange":"-0.7681","totalSupply":"10000","name":"Sappy Seals","id":"640794269434580993","url":"https://public.nftstatic.com/static/nft/res/nft-cex/S3/1667542059838_3hroxtrh283yvhqwq8qf5iydga25dpk9.png"},{"floorPrice":"1461.48","volume":"1.7789246322507268","numOwners":"2049","volumeChange":"0.22769999999999999","totalSupply":"7707","name":"Kanpai Pandas","id":"668552893376839681","url":"https://public.nftstatic.com/static/nft/res/nft-cex/S3/1674160231524_iprtxuwr3k0i4mkau3lhk8ig6nd4hvkv.gif"},{"floorPrice":"530.54","volume":"0.744240494123594","numOwners":"541","volumeChange":"0.3368","totalSupply":"2000","name":"San FranTokyo Genesis Pass","id":"746145329058648065","url":"https://public.nftstatic.com/static/nft/res/nft-extdata-loader/S3/1692659770288_1qoqg5x4vge5rq6jrx1brcxj5es1nh9g.jpg"},{"floorPrice":"4244.35","volume":"4.068393630102363","numOwners":"572","volumeChange":"-0.142","totalSupply":"3333","name":"The Grapes","id":"716286080416743425","url":"https://public.nftstatic.com/static/nft/res/nft-extdata-loader/S3/1685540770605_unr91be0qjnnib2d4zpgk0b7eco6sma8.jpg"},{"floorPrice":"242.45","volume":"0.2830066656135473","numOwners":"1166","volumeChange":"-0.3577","totalSupply":"585","name":"Ether Avatar","id":"731536572737953793","url":"https://public.nftstatic.com/static/nft/res/nft-extdata-loader/S3/1689566901298_gsgllydx488c9gvs2tgud6zn7aq456ib.jpg"},{"floorPrice":"578.19","volume":"0.5824754277770757","numOwners":"3389","volumeChange":"-0.0278","totalSupply":"10000","name":"a KID called BEAST","id":"667186301852073985","url":"https://public.nftstatic.com/static/nft/res/nft-cex/S3/1673834410745_8lovx1dxjo5q5cj04jt4ibuzkvhnbujw.png"},{"floorPrice":"58.06","volume":"0.09004157841526603","numOwners":"2","volumeChange":"1.4983000000000002","totalSupply":"47895","name":"The Seekers","id":"680738105300852737","url":"https://public.nftstatic.com/static/nft/res/nft-cex/S3/1677065412449_ew6df1n7c9q2x8sq4i7b10rpxuiqab50.png"},{"floorPrice":"533.84","volume":"0.5917920706432453","numOwners":"16054","volumeChange":"-0.2606","totalSupply":"0","name":"The Sandbox","id":"688009096191889409","url":"https://public.nftstatic.com/static/nft/res/nft-cex/S3/1678798951772_mg0wbx0v4jd1k5xjoh4876pg6nhbdxwf.png"},{"floorPrice":"174.18","volume":"0.14908953936560093","numOwners":"849","volumeChange":"-0.6388","totalSupply":"3333","name":"Skyborne - Nexian Gems","id":"734764074398892033","url":"https://public.nftstatic.com/static/nft/res/nft-extdata-loader/S3/1689946330913_hi8avbupzoisif73e7zjtr3t1x7r8rib.gif"},{"floorPrice":"98.1","volume":"0.13232332806773664","numOwners":"2032","volumeChange":"0.0209","totalSupply":"13888","name":"Imaginary Rides","id":"709344088172728321","url":"https://public.nftstatic.com/static/nft/res/nft-extdata-loader/S3/1683885731934_3k673uorkq7zu17sw68fuezeqclta5hz.jpg"},{"floorPrice":"55476.81","volume":"59.92640632819412","numOwners":"5704","volumeChange":"-0.7809999999999999","totalSupply":"10000","name":"Bored Ape Yacht Club","id":"505570382194139137","url":"https://public.nftstatic.com/static/nft/res/7c2bdc6c55a84d2aaff2f348522825cc.png"},{"floorPrice":"264.27","volume":"0.24478335713383043","numOwners":"274","volumeChange":"2.8279","totalSupply":"3433","name":"Delabs Adventure Pass Official","id":"696498191439306753","url":"https://public.nftstatic.com/static/nft/res/nft-extdata-loader/S3/1680822970347_kqai0dokuzcdv4ouz2idktp3es6wi7uj.jpg"},{"floorPrice":"16.0","volume":"0.11850400353848098","numOwners":"1228","volumeChange":"23.9859","totalSupply":"6000","name":"Time's End","id":"114349803269429248","url":"https://public.nftstatic.com/static/nft/res/1636894597414537a247c058b1752529.jpeg"},{"floorPrice":"1480.0","volume":"0.9348450473903703","numOwners":"127","volumeChange":"-0.5760000000000001","totalSupply":"0","name":"Mavia Land NFTs","id":"548137737250500609","url":"https://public.nftstatic.com/static/nft/res/f4fa02b24db9429a9ff42c3d04cd19b0.png"},{"floorPrice":"79.86","volume":"0.07666454757993177","numOwners":"713","volumeChange":"3.8251999999999997","totalSupply":"3000","name":"Kawamii Teens","id":"720445978477879297","url":"https://public.nftstatic.com/static/nft/res/nft-extdata-loader/S3/1686532570912_7robuganabkafxgh4jp024qrxvuv3yvg.jpg"},{"floorPrice":"436.45","volume":"0.4881498117022621","numOwners":"2934","volumeChange":"-0.4703","totalSupply":"8774","name":"RENGA","id":"640789951180509185","url":"https://public.nftstatic.com/static/nft/res/nft-cex/S3/1667541030366_d35qwj7v9lp5ybyp240ud5a5r5gnqjr8.gif"},{"floorPrice":"0.39","volume":"9.793573865790473E-4","numOwners":"41927","volumeChange":"-0.9239","totalSupply":"602065","name":"X World Games","id":"508700038943432705","url":"https://public.nftstatic.com/static/nft/res/77973d141adf41bea255db516a96348d.png"},{"floorPrice":"787.61","volume":"0.7059405952230507","numOwners":"1233","volumeChange":"-0.4089","totalSupply":"5431","name":"Checks - VV Edition","id":"667186315421179905","url":"https://public.nftstatic.com/static/nft/res/nft-cex/S3/1673834413975_66tumrmx9me89vhy57veg2l1w5qf49fu.png"},{"floorPrice":"177.98","volume":"0.18954156893719198","numOwners":"3700","volumeChange":"-0.22949999999999998","totalSupply":"11914","name":"NFT Worlds Genesis Avatars","id":"700888436944719873","url":"https://public.nftstatic.com/static/nft/res/nft-extdata-loader/S3/1681869730442_bymgfw4y6pvn16qmwk15jtfw3k02fd5l.jpg"},{"floorPrice":"17.42","volume":"0.017884599393403262","numOwners":"12","volumeChange":"2.218","totalSupply":"29963","name":"MERGE VV","id":"671772778938806273","url":"https://public.nftstatic.com/nft/temp/cex/nft-cex/S3/1674927911531_70d74t7eg930ogriq8mt3zqqbxckaalc.svg"},{"floorPrice":"169.97","volume":"0.22839783899911537","numOwners":"2827","volumeChange":"-0.1559","totalSupply":"9999","name":"Genuine Undead","id":"640795709716135937","url":"https://public.nftstatic.com/static/nft/res/nft-cex/S3/1667877189894_u7ygmd1rdggcybdliw5v3xjmr4q9c7lk.jpg"},{"floorPrice":"2782.65","volume":"3.3582097807405535","numOwners":"1686","volumeChange":"2.6824","totalSupply":"10000","name":"TOPIA Worlds","id":"707124470859243521","url":"https://public.nftstatic.com/static/nft/res/nft-extdata-loader/S3/1683357610517_52taqzmdem01tmeo1gxy7mfo4314q37o.jpg"},{"floorPrice":"238.24","volume":"0.13153719069885","numOwners":"7","volumeChange":"-0.7390000000000001","totalSupply":"0","name":"KPR","id":"664790673723109376","url":"https://public.nftstatic.com/static/nft/res/ff69bc17499540388fb659be5a65b094.jpeg"},{"floorPrice":"9.01","volume":"0.02663358587135094","numOwners":"360","volumeChange":"-0.020499999999999997","totalSupply":"12227","name":"Dimension X","id":"746107575269625857","url":"https://public.nftstatic.com/static/nft/res/nft-extdata-loader/S3/1692650770279_v6xkf3eeleqqmhef2xk28cyvzo5yivrc.jpg"},{"floorPrice":"333.34","volume":"0.3454479950714015","numOwners":"6553","volumeChange":"-0.2849","totalSupply":"16068","name":"Otherside Vessels","id":"696169778363047937","url":"https://public.nftstatic.com/static/nft/res/nft-extdata-loader/S3/1680744730441_4lg38ehc0z91k4qmw66teiz4xj5f9ozz.jpg"},{"floorPrice":"39.44","volume":"0.04115706179704284","numOwners":"6951","volumeChange":"-0.2723","totalSupply":"34508","name":"XENFT by XEN CRYPTO","id":"668696373739745281","url":"https://public.nftstatic.com/static/nft/res/nft-cex/S3/1674194439942_o5yia6cpospatwt600hpjhdql4a74dsf.png"},{"floorPrice":"28.83","volume":"0.03170524832554025","numOwners":"3286","volumeChange":"0.1909","totalSupply":"10000","name":"Rebel Bots","id":"701511260512243713","url":"https://public.nftstatic.com/static/nft/res/nft-extdata-loader/S3/1682018170331_2swklgldo4qhlcnsrbd82nrzqduuu7yc.gif"},{"floorPrice":"1.88","volume":"0.008006973335018324","numOwners":"2872","volumeChange":"2.488","totalSupply":"14259","name":"WIN NFT HERO","id":"618017322892853248","url":"https://public.nftstatic.com/static/nft/res/e29b8c75f5824a908547898341d1e7a3.jpeg"},{"floorPrice":"30.03","volume":"0.024323819031972702","numOwners":"2847","volumeChange":"-0.1436","totalSupply":"9000","name":"FF6000","id":"716769258414362625","url":"https://public.nftstatic.com/static/nft/res/nft-extdata-loader/S3/1685655971259_9i4cxniyzjv1l1e6a8it6w3bzox0n43l.jpg"},{"floorPrice":"169.17","volume":"0.11814313913812714","numOwners":"3153","volumeChange":"0.2796","totalSupply":"8888","name":"Space Riders NFT","id":"698608342117175296","url":"https://public.nftstatic.com/static/nft/res/nft-extdata-loader/S3/1681326130432_b5t4aumix9wfkdujdj1glqi8sv8evchr.jpg"},{"floorPrice":"448.46","volume":"0.2556068949829395","numOwners":"1","volumeChange":"8.3325","totalSupply":"10000","name":"Lost Miners of the Ether","id":"677597444803051521","url":"https://public.nftstatic.com/static/nft/res/nft-cex/S3/1676316620652_97x2w0h8n96wxmxanxly6o627x4dg1ad.png"},{"floorPrice":"1381.21","volume":"1.1882404941235942","numOwners":"5730","volumeChange":"-0.45189999999999997","totalSupply":"10021","name":"mfers","id":"619382785107288064","url":"https://public.nftstatic.com/static/nft/res/5332395a05fc4826b6b19c87118f90eb.png"},{"floorPrice":"1420.45","volume":"0.9336145576898773","numOwners":"1126","volumeChange":"-0.6858","totalSupply":"3333","name":"Sproto Gremlins","id":"716712639836319745","url":"https://public.nftstatic.com/static/nft/res/nft-extdata-loader/S3/1685642530493_5vccjl2p8zf4olfz4lhpa27bskb5avlr.gif"},{"floorPrice":"1841.89","volume":"1.2568761474788324","numOwners":"5623","volumeChange":"-0.7924","totalSupply":"9965","name":"Cool Cats NFT","id":"619803992157577216","url":"https://public.nftstatic.com/static/nft/res/d1591836d6d44daf80b61960cda79893.png"},{"floorPrice":"608.62","volume":"0.45930609882471884","numOwners":"1874","volumeChange":"-0.0668","totalSupply":"10000","name":"Kubz","id":"662917212174016513","url":"https://public.nftstatic.com/static/nft/res/nft-cex/S3/1672816580476_glax7i9b1b0n2k5jiczlro0gsscsdv0p.gif"},{"floorPrice":"0.0","volume":"0.15186225199039557","numOwners":"155","volumeChange":"-0.8843000000000001","totalSupply":"250","name":"PRELUDES by Trevor Paglen","id":"696045259064676353","url":"https://public.nftstatic.com/static/nft/res/nft-extdata-loader/S3/1680714971529_yx82fxye6ltuutcz61uhnyqky80q67xp.jpg"},{"floorPrice":"500.51","volume":"0.5114271262479464","numOwners":"406","volumeChange":"0.1038","totalSupply":"12607","name":"OCM Karma","id":"676155436712349697","url":"https://public.nftstatic.com/static/nft/res/nft-cex/S3/1675972819139_2xn9g201kq42u28p72fcuqib9sht9927.png"},{"floorPrice":"0.13","volume":"0.005730559206369267","numOwners":"210487","volumeChange":"1.6602000000000001","totalSupply":"2500000","name":"NFT Passport Collection","id":"639337213600321536","url":"https://public.nftstatic.com/static/nft/res/d85eec3768b14b149f124a9046143303.png"},{"floorPrice":"473.69","volume":"0.3577402685454316","numOwners":"8614","volumeChange":"-0.5512","totalSupply":"28275","name":"HV-MTL","id":"688529436169109505","url":"https://public.nftstatic.com/static/nft/res/nft-cex/S3/1678923010526_splge3rvc3uwgok6mvdm56xog6e42fg3.png"},{"floorPrice":"4604.71","volume":"3.063974622772653","numOwners":"2942","volumeChange":"0.3015","totalSupply":"9500","name":"OnChainMonkey","id":"657544860888612865","url":"https://public.nftstatic.com/static/nft/res/nft-cex/S3/1671535712090_31mm1deppy16n8syg9hfiy6p5du35eav.jpg"},{"floorPrice":"2202.26","volume":"1.3485754151396439","numOwners":"5525","volumeChange":"-0.19190000000000002","totalSupply":"10000","name":"World of Women","id":"533653360898895873","url":"https://public.nftstatic.com/static/nft/res/6afa75b151d54176b839e05038f589db.gif"},{"floorPrice":"854.47","volume":"0.5315660343738152","numOwners":"1","volumeChange":"0.019799999999999998","totalSupply":"5555","name":"Azra Games - The Hopeful","id":"679979349445599233","url":"https://public.nftstatic.com/static/nft/res/nft-cex/S3/1676884510955_uu0ecmurm7osqcakpqosv2hhbxc54xjc.gif"},{"floorPrice":"2.4","volume":"7.32971060280551E-4","numOwners":"103","volumeChange":"0.0","totalSupply":"656","name":"CRYPTO HEROES","id":"663825640184754176","url":"https://public.nftstatic.com/static/nft/res/nft-cex/S3/1679254250273_b34i06dsbqmetgopfq4zhep409spfhn8.gif"},{"floorPrice":"20.02","volume":"0.032463757740427146","numOwners":"1291","volumeChange":"0.0","totalSupply":"4200","name":"TURBOTOADS","id":"711208871993876481","url":"https://public.nftstatic.com/static/nft/res/nft-extdata-loader/S3/1684330330564_r8fsxyu60t2vdhbimgo4a9nowoembnp0.gif"},{"floorPrice":"157.96","volume":"0.3752352799191205","numOwners":"1311","volumeChange":"-8.0E-4","totalSupply":"5148","name":"Sybil Samurai","id":"718218804508082177","url":"https://public.nftstatic.com/static/nft/res/nft-extdata-loader/S3/1686001571042_pw10695k0a3wwd9m4a0c289zanv19hfd.jpg"},{"floorPrice":"0.67","volume":"5.780980664728927E-4","numOwners":"237550","volumeChange":"0.36200000000000004","totalSupply":"1423597","name":"CR7 Mystery Box Collection","id":"289640760524506112","url":"https://public.nftstatic.com/static/nft/res/666b173a8a4d478abddbd398c2b70962.png"},{"floorPrice":"670.69","volume":"0.37422094717553395","numOwners":"6505","volumeChange":"-0.2169","totalSupply":"16670","name":"RTFKT Animus Egg 🥚","id":"668560421432160257","url":"https://public.nftstatic.com/static/nft/res/nft-cex/S3/1674162026371_r6meix177whxwbk4syb3119bzswb3vy7.gif"},{"floorPrice":"40.82","volume":"0.024957725894098323","numOwners":"0","volumeChange":"0.6221","totalSupply":"16999","name":"end of sartoshi - eos pass","id":"693338630591410177","url":"https://public.nftstatic.com/static/nft/res/nft-cex/S3/1680069611790_b7wpdm7uzn6i2vz7i1j6to05y9g1ogc8.png"},{"floorPrice":"2.37","volume":"0.0017901680778465818","numOwners":"2229","volumeChange":"7.802899999999999","totalSupply":"20000","name":"Seascape Zombie Fighter Mystery Box","id":"118623025485834240","url":"https://public.nftstatic.com/static/nft/res/930cfe440d044c4e9b0b817feb3eab99.jpeg"}]