[{"floorPrice":"0.18","volume":"0.008354469743649933","numOwners":"30153","volumeChange":"-0.0518","totalSupply":"144000","name":"Alpine Race Collectibles","id":"692959699477970944","url":"https://public.nftstatic.com/static/nft/res/c5a578c386684132a36d17e5c3735df0.png"},{"floorPrice":"6.87","volume":"0.01897199319268801","numOwners":"91","volumeChange":"0.5606","totalSupply":"238","name":"Homie Metaverse","id":"746406346941050880","url":"https://public.nftstatic.com/static/nft/res/nft-cex/S3/1698945075043_gzi3o57k2181mf2tc0bh2ukug9kqjlah.gif"},{"floorPrice":"16.45","volume":"0.017585487515037704","numOwners":"117","volumeChange":"39.4043","totalSupply":"264","name":"Bitcoin Punk Ordinal NFT (BTC)","id":"709714422037364736","url":"https://public.nftstatic.com/static/nft/res/nft-cex/S3/1699804648073_62u2t6o8po4itdnmwbv6zn7ytjw4vjmy.gif"},{"floorPrice":"18.49","volume":"0.017861090734818032","numOwners":"120","volumeChange":"93.1326","totalSupply":"260","name":"Hero Metaverse","id":"700672909955403776","url":"https://public.nftstatic.com/static/nft/res/nft-cex/S3/1690209943327_30idxysl3vtka4cg38awsg90w2epxxa3.gif"},{"floorPrice":"9.0","volume":"0.0172272771730094","numOwners":"69","volumeChange":"0.9843999999999999","totalSupply":"192","name":"Bitcoin Holders","id":"748922437476036608","url":"https://public.nftstatic.com/static/nft/res/nft-cex/S3/1700568513419_cyof2jo08caex7durmpi923sp8rk1f4z.gif"},{"floorPrice":"15.0","volume":"0.011644288606554974","numOwners":"51","volumeChange":"2.2997","totalSupply":"300","name":"Metaverse Ape Yacht Club","id":"753770820135309313","url":"https://public.nftstatic.com/static/nft/res/nft-cex/S3/1694477256483_uhqm3lxlpji6zybii8m38s1ktmsembnu.gif"},{"floorPrice":"1308.28","volume":"11.585973416272996","numOwners":"4727","volumeChange":"2.7123000000000004","totalSupply":"14335","name":"Azuki Elementals","id":"726319061462085633","url":"https://public.nftstatic.com/static/nft/res/nft-extdata-loader/S3/1687932850971_35r93kq25q763r0zvu5o5lg7id729hej.jpg"},{"floorPrice":"7247.73","volume":"56.181619913832726","numOwners":"2521","volumeChange":"1.4628","totalSupply":"8683","name":"DeGods","id":"694369170047053825","url":"https://public.nftstatic.com/static/nft/res/nft-cex/S3/1680315311520_bbkd4ll4i5ylykbam34twi0omc736x8p.png"},{"floorPrice":"11747.87","volume":"89.69304316774742","numOwners":"11490","volumeChange":"1.2765","totalSupply":"19486","name":"Mutant Ape Yacht Club","id":"505303452945186817","url":"https://public.nftstatic.com/static/nft/res/2c66a6e10df04bbea3eff518e06f8d73.jpeg"},{"floorPrice":"11.93","volume":"0.008109462750506148","numOwners":"80","volumeChange":"8.8163","totalSupply":"191","name":"Axies Infinity NFTs: AXS XRP BTC","id":"699235882968514560","url":"https://public.nftstatic.com/static/nft/res/nft-cex/S3/1700904156457_hps5n229xlt32izsnbhq35xxlllaw8of.gif"},{"floorPrice":"13.49","volume":"0.0069943370206273295","numOwners":"111","volumeChange":"-0.7445999999999999","totalSupply":"266","name":"Anime Warrior","id":"747520513872703488","url":"https://public.nftstatic.com/static/nft/res/nft-cex/S3/1699442961647_bapqxbfaxc8nrt3wkvlvcxllgdleokgy.gif"},{"floorPrice":"4377.09","volume":"25.045453472120343","numOwners":"6086","volumeChange":"1.5691","totalSupply":"10000","name":"Moonbirds","id":"569066442241241089","url":"https://public.nftstatic.com/static/nft/res/5966121f53a842f793d02d24cf196e1c.png"},{"floorPrice":"257.77","volume":"1.355499609753235","numOwners":"2","volumeChange":"686.8191","totalSupply":"7070","name":"Binary: DEX","id":"686060667337342977","url":"https://public.nftstatic.com/static/nft/res/nft-cex/S3/1678334410170_08j5xjmh3yjh7dy26tzt1u6div9pnwl1.gif"},{"floorPrice":"8.7","volume":"0.004956133916258326","numOwners":"122","volumeChange":"14.1943","totalSupply":"816","name":"MOTORCYCLE BABIES","id":"674576679284477953","url":"https://public.nftstatic.com/static/nft/res/nft-cex/S3/1694191221302_3400emcjpf0me4ejxp4s1apipdkzes9d.gif"},{"floorPrice":"714.54","volume":"3.2557343979538946","numOwners":"7895","volumeChange":"1.0798999999999999","totalSupply":"19950","name":"BEANZ Official","id":"641881145226350593","url":"https://public.nftstatic.com/static/nft/res/nft-cex/S3/1667801191325_338ee699dzk7uo3meez6rkttidw9tvfc.png"},{"floorPrice":"921.32","volume":"4.277408962471759","numOwners":"4132","volumeChange":"-0.0581","totalSupply":"16000","name":"Opepen Edition","id":"668545431091167233","url":"https://public.nftstatic.com/static/nft/res/nft-cex/S3/1674158452400_vx3wp10xif320ent425wm1a378f7hr77.png"},{"floorPrice":"3685.08","volume":"14.934378430308186","numOwners":"5129","volumeChange":"4.1385000000000005","totalSupply":"9602","name":"Bored Ape Kennel Club","id":"641881108745592833","url":"https://public.nftstatic.com/static/nft/res/nft-cex/S3/1667801182515_w2evj8h6omdvfgozzfyru7oqwpfjr3tm.png"},{"floorPrice":"3112.02","volume":"13.296902322408382","numOwners":"9633","volumeChange":"0.7853","totalSupply":"19517","name":"CLONE X - X TAKASHI MURAKAMI","id":"533652760429920257","url":"https://public.nftstatic.com/static/nft/res/b8b7c6ac4743492db019ce26f7347462.jpeg"},{"floorPrice":"5.99","volume":"0.005001809414825464","numOwners":"109","volumeChange":"-0.514","totalSupply":"326","name":"Metaverse NFT Collection","id":"752553272268472320","url":"https://public.nftstatic.com/static/nft/res/nft-cex/S3/1694555455762_x9bwyzzo5kqvrnx7vqkiq2kai59c3d7t.gif"},{"floorPrice":"4.99","volume":"0.0044290073648073705","numOwners":"0","volumeChange":"0.133","totalSupply":"2622","name":"PRIME APE","id":"610426331564736512","url":"https://public.nftstatic.com/static/nft/res/nft-cex/S3/1662369499381_6ddhmk90crst776u8z4n1kk4rnldvibo.gif"},{"floorPrice":"743.2","volume":"2.677307091439023","numOwners":"544","volumeChange":"0.30820000000000003","totalSupply":"1000","name":"Velocity Series: Velocity Pass","id":"739705404534157313","url":"https://public.nftstatic.com/static/nft/res/nft-extdata-loader/S3/1691124371107_scjwjpzl08fxtxxprfehdxhcm4pkars2.jpg"},{"floorPrice":"0.15","volume":"8.730182017350822E-4","numOwners":"0","volumeChange":"-0.7773","totalSupply":"10004","name":"🙀 Voodoo Kitten 🙀","id":"601704584883970048","url":"https://public.nftstatic.com/static/nft/res/nft-cex/S3/1658299009140_852z65fwbcq84mbbpgdxb1wrluqme8jy.gif"},{"floorPrice":"1023.69","volume":"2.814704225228133","numOwners":"7539","volumeChange":"0.11130000000000001","totalSupply":"21279","name":"Lil Pudgys","id":"528399448512405505","url":"https://public.nftstatic.com/static/nft/res/448fce1fabc24a46b4a1cba661fec292.png"},{"floorPrice":"386.54","volume":"1.0954162602818776","numOwners":"5617","volumeChange":"0.3326","totalSupply":"20000","name":"Nakamigos","id":"690968054768242689","url":"https://public.nftstatic.com/static/nft/res/nft-cex/S3/1679504422444_vjcv41ljfw58vjy9hkcyarbkxjus3u2d.png"},{"floorPrice":"5.78","volume":"0.004423197187093494","numOwners":"339","volumeChange":"-0.7295","totalSupply":"628","name":"Rose Collection","id":"668759428913696768","url":"https://public.nftstatic.com/static/nft/res/nft-cex/S3/1686313208695_dom4t3byesa95h118zn520ugcd0pdplj.gif"},{"floorPrice":"6653.99","volume":"15.144778309517521","numOwners":"591","volumeChange":"5.261","totalSupply":"3333","name":"The Grapes","id":"716286080416743425","url":"https://public.nftstatic.com/static/nft/res/nft-extdata-loader/S3/1685540770605_unr91be0qjnnib2d4zpgk0b7eco6sma8.jpg"},{"floorPrice":"63243.57","volume":"154.54380995178155","numOwners":"5675","volumeChange":"1.1348","totalSupply":"10000","name":"Bored Ape Yacht Club","id":"505570382194139137","url":"https://public.nftstatic.com/static/nft/res/7c2bdc6c55a84d2aaff2f348522825cc.png"},{"floorPrice":"12284.28","volume":"30.818487683264383","numOwners":"4413","volumeChange":"0.7158","totalSupply":"8888","name":"Pudgy Penguins","id":"507850950909366272","url":"https://public.nftstatic.com/static/nft/res/9e9d1ca1a76847418c3a10ac13c627db.png"},{"floorPrice":"4631.17","volume":"10.73077501589351","numOwners":"5565","volumeChange":"1.0443","totalSupply":"10000","name":"Doodles","id":"533647159874920449","url":"https://public.nftstatic.com/static/nft/res/40d30afcdd6a49939e89bb124e4cf85c.jpeg"},{"floorPrice":"12888.26","volume":"27.537072283188095","numOwners":"4220","volumeChange":"1.0155","totalSupply":"10000","name":"Azuki","id":"566536999900893185","url":"https://public.nftstatic.com/static/nft/res/303d4787c96242a1bb000136dd57f405.jpeg"},{"floorPrice":"6823.92","volume":"11.03374623446104","numOwners":"649","volumeChange":"0.6261","totalSupply":"2061","name":"Matr1x 2061","id":"679892531327184897","url":"https://public.nftstatic.com/static/nft/res/4c5089f3346940d3aa9b9fe6b0b922f2.png"},{"floorPrice":"30.3","volume":"0.06739864831822227","numOwners":"45187","volumeChange":"0.1324","totalSupply":"94757","name":"Gemesis","id":"695709251536801793","url":"https://public.nftstatic.com/static/nft/res/nft-extdata-loader/S3/1680634925214_xtb6fk14mq6we8qt87wamdypf3uxs0uy.jpg"},{"floorPrice":"1048.26","volume":"2.0327076362195946","numOwners":"2546","volumeChange":"0.009399999999999999","totalSupply":"10000","name":"Redacted Remilio Babies","id":"668643429774356481","url":"https://public.nftstatic.com/static/nft/res/nft-cex/S3/1678261197262_an96jigwq039okugxmqdh4gjlqyrz9ch.gif"},{"floorPrice":"2067.85","volume":"4.212537975704938","numOwners":"5610","volumeChange":"3.8158","totalSupply":"9965","name":"Cool Cats NFT","id":"619803992157577216","url":"https://public.nftstatic.com/static/nft/res/d1591836d6d44daf80b61960cda79893.png"},{"floorPrice":"5259.72","volume":"8.936968492219517","numOwners":"3541","volumeChange":"0.457","totalSupply":"10000","name":"Milady Maker","id":"640794577033273345","url":"https://public.nftstatic.com/static/nft/res/nft-cex/S3/1667874736142_4iimvwacp4r3v0khr6j8sr2tlzyxs8zr.jpg"},{"floorPrice":"1167.01","volume":"1.8326193568263844","numOwners":"545","volumeChange":"5.0616","totalSupply":"2000","name":"San FranTokyo Genesis Pass","id":"746145329058648065","url":"https://public.nftstatic.com/static/nft/res/nft-extdata-loader/S3/1692659770288_1qoqg5x4vge5rq6jrx1brcxj5es1nh9g.jpg"},{"floorPrice":"859.9","volume":"1.576695224122923","numOwners":"1858","volumeChange":"6.7627999999999995","totalSupply":"10000","name":"Kubz","id":"662917212174016513","url":"https://public.nftstatic.com/static/nft/res/nft-cex/S3/1672816580476_glax7i9b1b0n2k5jiczlro0gsscsdv0p.gif"},{"floorPrice":"0.85","volume":"0.001818376319161214","numOwners":"237526","volumeChange":"2.9923","totalSupply":"1423597","name":"CR7 Mystery Box Collection","id":"289640760524506112","url":"https://public.nftstatic.com/static/nft/res/666b173a8a4d478abddbd398c2b70962.png"},{"floorPrice":"14.99","volume":"0.00231262286904727","numOwners":"57","volumeChange":"-0.8529000000000001","totalSupply":"150","name":"Bitcoin NFT -  BTC XRP SHIB DOGE","id":"708514458696572928","url":"https://public.nftstatic.com/static/nft/res/nft-cex/S3/1683691361454_tufg4hh65npe021cpfgexjupq4wsbvl3.gif"},{"floorPrice":"1289.85","volume":"2.601619066830981","numOwners":"3071","volumeChange":"-0.32380000000000003","totalSupply":"100000","name":"Otherdeed for Otherside","id":"641881071684722689","url":"https://public.nftstatic.com/static/nft/res/nft-cex/S3/1667801173679_6osf0fmr4zgqsgotq5zt40pzdm8njn3g.png"},{"floorPrice":"978.65","volume":"1.452126173918997","numOwners":"1971","volumeChange":"0.0437","totalSupply":"10000","name":"Sappy Seals","id":"640794269434580993","url":"https://public.nftstatic.com/static/nft/res/nft-cex/S3/1667542059838_3hroxtrh283yvhqwq8qf5iydga25dpk9.png"},{"floorPrice":"203.92","volume":"0.25833458085150085","numOwners":"7","volumeChange":"1.6528","totalSupply":"0","name":"KPR","id":"664790673723109376","url":"https://public.nftstatic.com/static/nft/res/ff69bc17499540388fb659be5a65b094.jpeg"},{"floorPrice":"0.45","volume":"0.003074635916395255","numOwners":"15334","volumeChange":"-0.6083","totalSupply":"50000","name":"The CR7 ForeverZone Box","id":"407802751394464768","url":"https://public.nftstatic.com/static/nft/res/c5c23ecbddc545348090905147dfb4ad.png"},{"floorPrice":"2108.8","volume":"2.3335137906751564","numOwners":"1542","volumeChange":"-0.1912","totalSupply":"5564","name":"Azuki Elemental Beans","id":"726020668084563969","url":"https://public.nftstatic.com/static/nft/res/0ac510b4d43d490eb847787c7f67b4c2.jpeg"},{"floorPrice":"343.14","volume":"0.5109185117807576","numOwners":"2041","volumeChange":"4.7225","totalSupply":"7393","name":"Moonbirds: Mythics","id":"734892440581369857","url":"https://public.nftstatic.com/static/nft/res/nft-extdata-loader/S3/1689976930338_qg1pg6tvcd6pyf75p7lek9u2usrmvmfm.jpg"},{"floorPrice":"1945.01","volume":"2.9950428229805466","numOwners":"2722","volumeChange":"0.021099999999999997","totalSupply":"11911","name":"Pixelmon - Generation 1","id":"657544850517258241","url":"https://public.nftstatic.com/static/nft/res/nft-cex/S3/1671538727863_qtij3ornjpwcekfcj5scq96jy0fgctoy.gif"},{"floorPrice":"1.37","volume":"0.001468560194829964","numOwners":"0","volumeChange":"0.0","totalSupply":"2227","name":"Okay Monkeys","id":"616750763220799488","url":""},{"floorPrice":"2864.2","volume":"4.046689347926019","numOwners":"6601","volumeChange":"0.2894","totalSupply":"20000","name":"Meebits","id":"620207919082143744","url":"https://public.nftstatic.com/static/nft/res/5bc971125c4640b0be2ddb6f08ee1367.png"},{"floorPrice":"245.69","volume":"0.25619475758731647","numOwners":"838","volumeChange":"0.9109","totalSupply":"3333","name":"Skyborne - Nexian Gems","id":"734764074398892033","url":"https://public.nftstatic.com/static/nft/res/nft-extdata-loader/S3/1689946330913_hi8avbupzoisif73e7zjtr3t1x7r8rib.gif"},{"floorPrice":"0.45","volume":"0.003065004450182409","numOwners":"41933","volumeChange":"-0.7058","totalSupply":"602065","name":"X World Games","id":"508700038943432705","url":"https://public.nftstatic.com/static/nft/res/77973d141adf41bea255db516a96348d.png"},{"floorPrice":"16.38","volume":"0.03134115049441038","numOwners":"2846","volumeChange":"1.824","totalSupply":"9000","name":"FF6000","id":"716769258414362625","url":"https://public.nftstatic.com/static/nft/res/nft-extdata-loader/S3/1685655971259_9i4cxniyzjv1l1e6a8it6w3bzox0n43l.jpg"},{"floorPrice":"8883.58","volume":"11.783712362215509","numOwners":"4009","volumeChange":"-0.6106","totalSupply":"9999","name":"The Captainz","id":"664106493958045697","url":"https://public.nftstatic.com/static/nft/res/nft-cex/S3/1673100127317_ftyn7zwf6v3raznvt22ayl2k1f1t6kk4.png"},{"floorPrice":"1328.75","volume":"1.2428707745273515","numOwners":"1224","volumeChange":"1.2389000000000001","totalSupply":"5415","name":"Checks - VV Edition","id":"667186315421179905","url":"https://public.nftstatic.com/static/nft/res/nft-cex/S3/1673834413975_66tumrmx9me89vhy57veg2l1w5qf49fu.png"},{"floorPrice":"1.9","volume":"0.0012286953630077366","numOwners":"355","volumeChange":"2.6912000000000003","totalSupply":"1314","name":"CRYPTO WARRİORS","id":"622420866966917121","url":"https://public.nftstatic.com/static/nft/res/nft-cex/S3/1663161146680_8bzzsi2ksaw2ayyv2przaksz36ype4hk.jpeg"},{"floorPrice":"12.0","volume":"0.001377644924346899","numOwners":"197","volumeChange":"8.0874","totalSupply":"818","name":"NEON CUTS","id":"671432400327327744","url":"https://public.nftstatic.com/static/nft/res/nft-cex/S3/1694190902316_zi85kmtk2gfkgrrvp3ghiczcz6o6aksc.gif"},{"floorPrice":"583.5","volume":"1.5012362890369024","numOwners":"12789","volumeChange":"0.2026","totalSupply":"52428","name":"Otherdeed Expanded","id":"696173597875834881","url":"https://public.nftstatic.com/static/nft/res/nft-extdata-loader/S3/1680745570357_kwuoqkwgcwdqu2fobh7erh298y7lz43m.jpg"},{"floorPrice":"429.54","volume":"0.5755334164686091","numOwners":"2930","volumeChange":"0.2799","totalSupply":"8774","name":"RENGA","id":"640789951180509185","url":"https://public.nftstatic.com/static/nft/res/nft-cex/S3/1667541030366_d35qwj7v9lp5ybyp240ud5a5r5gnqjr8.gif"},{"floorPrice":"34.81","volume":"0.04722735981925413","numOwners":"2207","volumeChange":"59.5113","totalSupply":"7777","name":"Kandyland","id":"696739778014744576","url":"https://public.nftstatic.com/static/nft/res/nft-extdata-loader/S3/1680880570454_45wtm4cu1xba1kpzkwzthcrzf2v3ali9.jpg"},{"floorPrice":"18.02","volume":"0.02606541572528193","numOwners":"12","volumeChange":"0.8589","totalSupply":"29963","name":"MERGE VV","id":"671772778938806273","url":"https://public.nftstatic.com/nft/temp/cex/nft-cex/S3/1674927911531_70d74t7eg930ogriq8mt3zqqbxckaalc.svg"},{"floorPrice":"399.24","volume":"0.44630015208865154","numOwners":"1071","volumeChange":"2.6382999999999996","totalSupply":"10000","name":"Ordinal Kubz","id":"685341461071519745","url":"https://public.nftstatic.com/static/nft/res/nft-cex/S3/1678162938013_czqi6f7vkntl720g9qvg30dwhp3jzg8x.gif"},{"floorPrice":"332.7","volume":"0.4083320197959763","numOwners":"6515","volumeChange":"0.4293","totalSupply":"15779","name":"Otherside Vessels","id":"696169778363047937","url":"https://public.nftstatic.com/static/nft/res/nft-extdata-loader/S3/1680744730441_4lg38ehc0z91k4qmw66teiz4xj5f9ozz.jpg"},{"floorPrice":"0.0","volume":"1.3310204185127588","numOwners":"1206","volumeChange":"6.1792","totalSupply":"10420","name":"Impostors Genesis Aliens","id":"642015686716870657","url":"https://public.nftstatic.com/static/nft/res/nft-cex/S3/1667833268419_e0vmx58ravbk75us7h79i932gv6qwr5o.webp"},{"floorPrice":"6.96","volume":"0.027325978306583332","numOwners":"3164","volumeChange":"-0.49920000000000003","totalSupply":"25115","name":"The Syphon","id":"189627778021383168","url":"https://public.nftstatic.com/static/nft/res/b5a02a493f354d109f1e08eff0b69e79.jpeg"},{"floorPrice":"1432.96","volume":"1.4669523272986904","numOwners":"5726","volumeChange":"0.4023","totalSupply":"10021","name":"mfers","id":"619382785107288064","url":"https://public.nftstatic.com/static/nft/res/5332395a05fc4826b6b19c87118f90eb.png"},{"floorPrice":"4.0","volume":"0.018998034095243685","numOwners":"6940","volumeChange":"-0.7212000000000001","totalSupply":"40250","name":"The Infinity Vault","id":"140242452236967936","url":"https://public.nftstatic.com/static/nft/res/1c761fc2d4fb49c39f678ae6f0cf816f.jpeg"},{"floorPrice":"0.0","volume":"0.145533068767544","numOwners":"0","volumeChange":"-0.43189999999999995","totalSupply":"9795","name":"8liens NFT","id":"641536435656134656","url":"https://public.nftstatic.com/static/nft/res/nft-cex/S3/1667877683893_teh78l5o4xsx7e89xn6xvpuwcyk746eq.gif"},{"floorPrice":"2.5","volume":"0.0010845436851422592","numOwners":"38","volumeChange":"-0.7843000000000001","totalSupply":"148","name":"GODDESS NFT","id":"664413273701097473","url":"https://public.nftstatic.com/static/nft/res/nft-cex/S3/1700610270164_defn1yc2qbqk5wh5vrkmp9t3171gngxt.gif"},{"floorPrice":"2.6","volume":"7.551602554698122E-4","numOwners":"108","volumeChange":"0.3312","totalSupply":"656","name":"CRYPTO HEROES","id":"663825640184754176","url":"https://public.nftstatic.com/static/nft/res/nft-cex/S3/1679254250273_b34i06dsbqmetgopfq4zhep409spfhn8.gif"},{"floorPrice":"0.73","volume":"0.0013073266629500307","numOwners":"6309","volumeChange":"0.616","totalSupply":"50000","name":"Fall Harvest Party with Alice","id":"137367227396677632","url":"https://public.nftstatic.com/static/nft/res/221aa9dcea754e00bd0fca139b0f07f3.jpeg"},{"floorPrice":"2047.38","volume":"1.6288399665502775","numOwners":"0","volumeChange":"3.0812","totalSupply":"2000","name":"Oh Ottie!","id":"675649623394525185","url":"https://public.nftstatic.com/static/nft/res/nft-cex/S3/1675852223820_w5amaa3vrimv452ral6oekwcu3p0uhi9.gif"},{"floorPrice":"1131.72","volume":"0.8023227986268009","numOwners":"3322","volumeChange":"2.2565","totalSupply":"10420","name":"Treeverse Plots","id":"640790042729156609","url":"https://public.nftstatic.com/static/nft/res/nft-cex/S3/1667541052115_gnp9ih8fn60e3g6u42qccdukigamspxi.png"},{"floorPrice":"0.13","volume":"0.002599991686472423","numOwners":"210501","volumeChange":"-0.3857","totalSupply":"2500000","name":"NFT Passport Collection","id":"639337213600321536","url":"https://public.nftstatic.com/static/nft/res/d85eec3768b14b149f124a9046143303.png"},{"floorPrice":"4238.08","volume":"4.140384576450222","numOwners":"2966","volumeChange":"1.067","totalSupply":"9500","name":"OnChainMonkey","id":"657544860888612865","url":"https://public.nftstatic.com/static/nft/res/nft-cex/S3/1671535712090_31mm1deppy16n8syg9hfiy6p5du35eav.jpg"},{"floorPrice":"57.32","volume":"0.0372628453781677","numOwners":"3","volumeChange":"3.0075","totalSupply":"16550","name":"Genesis Box","id":"663726950074187776","url":"https://public.nftstatic.com/static/nft/res/nft-cex/S3/1673009637013_ihm2khge8kue2pccm6eecp0qoii06v49.png"},{"floorPrice":"163.79","volume":"0.2587825278992205","numOwners":"2841","volumeChange":"0.6282","totalSupply":"9999","name":"Genuine Undead","id":"640795709716135937","url":"https://public.nftstatic.com/static/nft/res/nft-cex/S3/1667877189894_u7ygmd1rdggcybdliw5v3xjmr4q9c7lk.jpg"},{"floorPrice":"1865.16","volume":"1.5306928528114394","numOwners":"2041","volumeChange":"0.2804","totalSupply":"7707","name":"Kanpai Pandas","id":"668552893376839681","url":"https://public.nftstatic.com/static/nft/res/nft-cex/S3/1674160231524_iprtxuwr3k0i4mkau3lhk8ig6nd4hvkv.gif"},{"floorPrice":"1697.28","volume":"1.3216960466731218","numOwners":"2144","volumeChange":"-0.6328","totalSupply":"11001","name":"Parallel Avatars","id":"729456622577106945","url":"https://public.nftstatic.com/static/nft/res/nft-extdata-loader/S3/1689566900605_frdc23351j48m7gts0o4hy7kymy1z59x.jpg"},{"floorPrice":"62.9","volume":"0.05333826374421721","numOwners":"477","volumeChange":"-0.5588000000000001","totalSupply":"10000","name":"Block Legends","id":"718120215278723072","url":"https://public.nftstatic.com/static/nft/res/6d29b3b8bc4f449ba4a6d93ba8319647.png"},{"floorPrice":"552.79","volume":"0.4564749616110639","numOwners":"3389","volumeChange":"0.2577","totalSupply":"10000","name":"a KID called BEAST","id":"667186301852073985","url":"https://public.nftstatic.com/static/nft/res/nft-cex/S3/1673834410745_8lovx1dxjo5q5cj04jt4ibuzkvhnbujw.png"},{"floorPrice":"4.0","volume":"8.174936181450075E-4","numOwners":"57","volumeChange":"0.0","totalSupply":"249","name":"DOODLE APE","id":"666719112752467969","url":"https://public.nftstatic.com/static/nft/res/nft-cex/S3/1700691745419_9167eq4zcecll8iep0wkup2kenwuo0lg.gif"},{"floorPrice":"280.49","volume":"0.25071033958315","numOwners":"2","volumeChange":"0.0652","totalSupply":"8888","name":"Ninja Squad Official","id":"668567990451990529","url":"https://public.nftstatic.com/static/nft/res/nft-cex/S3/1674163830963_w4j853y6degimoiihixeezdzda3mqots.png"},{"floorPrice":"487.27","volume":"0.6549782498557358","numOwners":"406","volumeChange":"0.9842","totalSupply":"12629","name":"OCM Karma","id":"676155436712349697","url":"https://public.nftstatic.com/static/nft/res/nft-cex/S3/1675972819139_2xn9g201kq42u28p72fcuqib9sht9927.png"},{"floorPrice":"153.55","volume":"0.08795511281945952","numOwners":"2760","volumeChange":"6.4891","totalSupply":"10674","name":"FVCK_AVATAR//","id":"725308016576151553","url":"https://public.nftstatic.com/static/nft/res/nft-extdata-loader/S3/1687691770464_iy16cw282s84b8nwtyn5oqw154eomhot.jpg"},{"floorPrice":"325.53","volume":"0.1997507296343026","numOwners":"1142","volumeChange":"-0.1602","totalSupply":"585","name":"Ether Avatar","id":"731536572737953793","url":"https://public.nftstatic.com/static/nft/res/nft-extdata-loader/S3/1689566901298_gsgllydx488c9gvs2tgud6zn7aq456ib.jpg"},{"floorPrice":"3621.82","volume":"2.4439219741204776","numOwners":"2812","volumeChange":"-0.5911","totalSupply":"9999","name":"The Potatoz","id":"627028585490763776","url":"https://public.nftstatic.com/static/nft/res/b4bf0e0b2b9a406eaa4787f21a5b2706.gif"},{"floorPrice":"5097.98","volume":"3.0753791741243903","numOwners":"2113","volumeChange":"0.9390999999999999","totalSupply":"8888","name":"Mocaverse","id":"687588315884740608","url":"https://public.nftstatic.com/static/nft/res/61ca8908746a49518229060820474f2e.gif"},{"floorPrice":"1295.36","volume":"0.6382040609137056","numOwners":"1","volumeChange":"1.0733","totalSupply":"5555","name":"Azra Games - The Hopeful","id":"679979349445599233","url":"https://public.nftstatic.com/static/nft/res/nft-cex/S3/1676884510955_uu0ecmurm7osqcakpqosv2hhbxc54xjc.gif"},{"floorPrice":"0.68","volume":"3.9565740441888445E-4","numOwners":"0","volumeChange":"6.2692","totalSupply":"14806","name":"PEPE CLUB","id":"599166106115051520","url":"https://public.nftstatic.com/static/nft/res/nft-cex/S3/1657618911265_finrknlq3lmc7p9toib7bl3cmwcuuyuc.gif"},{"floorPrice":"272.3","volume":"0.15642605508445567","numOwners":"268","volumeChange":"0.42979999999999996","totalSupply":"3433","name":"Delabs Adventure Pass Official","id":"696498191439306753","url":"https://public.nftstatic.com/static/nft/res/nft-extdata-loader/S3/1680822970347_kqai0dokuzcdv4ouz2idktp3es6wi7uj.jpg"},{"floorPrice":"1590.0","volume":"0.7067040359731229","numOwners":"126","volumeChange":"-0.1603","totalSupply":"0","name":"Mavia Land NFTs","id":"548137737250500609","url":"https://public.nftstatic.com/static/nft/res/f4fa02b24db9429a9ff42c3d04cd19b0.png"},{"floorPrice":"675.64","volume":"0.3651306001388848","numOwners":"6509","volumeChange":"0.2349","totalSupply":"16672","name":"RTFKT Animus Egg 🥚","id":"668560421432160257","url":"https://public.nftstatic.com/static/nft/res/nft-cex/S3/1674162026371_r6meix177whxwbk4syb3119bzswb3vy7.gif"},{"floorPrice":"265.95","volume":"0.1631957209784533","numOwners":"0","volumeChange":"33.3082","totalSupply":"8737","name":"Impostors Genesis Pets","id":"745594200095678465","url":"https://public.nftstatic.com/static/nft/res/nft-extdata-loader/S3/1692528370414_r2rqwlebklj47s54n0rwxvfal9289rqi.jpg"},{"floorPrice":"294.62","volume":"0.18204940925051105","numOwners":"2516","volumeChange":"0.9723999999999999","totalSupply":"9000","name":"Valhalla","id":"663727015325208577","url":"https://public.nftstatic.com/static/nft/res/nft-cex/S3/1673009652524_fjwmm63uod0xwcjpqm22yo660hw7g9di.png"},{"floorPrice":"3.5","volume":"8.203299981416821E-4","numOwners":"153","volumeChange":"-0.7767000000000001","totalSupply":"890","name":"THE CAGE","id":"663845917881667584","url":"https://public.nftstatic.com/static/nft/res/nft-cex/S3/1679526788029_zfdb3xmumsw9q3x19mkwbza0zhcr9hx1.gif"},{"floorPrice":"307.09","volume":"0.14304893440137711","numOwners":"2112","volumeChange":"1.8597","totalSupply":"0","name":"Rug Radio - Genesis NFT","id":"640793984944443393","url":"https://public.nftstatic.com/static/nft/res/nft-cex/S3/1667541992061_lkz2hsj62o0nz4egdfsjk2i6j4l271rx.png"},{"floorPrice":"2.4","volume":"0.0016858420625372888","numOwners":"7544","volumeChange":"0.0116","totalSupply":"28000","name":"ForeverCR7: The GOAT Box","id":"370827762959315968","url":"https://public.nftstatic.com/static/nft/res/d1b9a0efa0d94d919331b986f277f1a9.png"},{"floorPrice":"214.97","volume":"0.15261480443648956","numOwners":"8724","volumeChange":"0.8229000000000001","totalSupply":"20066","name":"ALTS by adidas","id":"692844154568654849","url":"https://public.nftstatic.com/static/nft/res/nft-cex/S3/1679951719465_3slit7lh161wl4hnzrc6079axrpu157r.png"},{"floorPrice":"450.42","volume":"0.2983574802186947","numOwners":"8574","volumeChange":"-0.1292","totalSupply":"28289","name":"HV-MTL","id":"688529436169109505","url":"https://public.nftstatic.com/static/nft/res/nft-cex/S3/1678923010526_splge3rvc3uwgok6mvdm56xog6e42fg3.png"},{"floorPrice":"388.39","volume":"0.18770395968428158","numOwners":"926","volumeChange":"1.3485","totalSupply":"4444","name":"Apes Together Strong Official NFT","id":"722827944283975681","url":"https://public.nftstatic.com/static/nft/res/nft-extdata-loader/S3/1687100530532_vs1khic24jvk69htx4ux4rgl9mkhsw4s.jpg"},{"floorPrice":"839.43","volume":"0.35272419725555787","numOwners":"2427","volumeChange":"2.1533","totalSupply":"7967","name":"Inhabitants: Generative Identities (MetaHero)","id":"640787498925871105","url":"https://public.nftstatic.com/static/nft/res/nft-cex/S3/1667540445654_39ibhh3s97ahz3ywkpyd1thzb8yfumun.png"}]